{"isSuccess":true,"data":{"original_data":[{"issue":"201810200780","lottery":["0","8","9","3","9"],"pair":[436,433],"leopard":[477,475,478],"group_three":[359,356,0],"group_six":[0,0,139],"total_val":[17,20,21,8,12],"bs_form":["011","110","101"],"oe_form":["001","011","111"],"pc_form":["000","001","010"],"other_form":["020","200","000"],"span":[9,6,6,8,6],"mantissa":[7,0,1,8,2],"miss_data":[["0",2,1,18,3,40,5,25,9,10],[1,5,4,3,13,21,10,24,8,9],[9,7,17,3,1,19,5,11,14,9],[12,1,16,3,3,5,7,2,15,8],[13,4,5,3,7,1,9,10,2,9]]},{"issue":"201810200779","lottery":["9","7","2","3","5"],"pair":[437,434],"leopard":[478,476,479],"group_three":[360,357,346],"group_six":[0,0,0],"total_val":[18,12,10,16,8],"bs_form":["110","100","001"],"oe_form":["110","101","011"],"pc_form":["011","111","111"],"other_form":["012","120","202"],"span":[7,5,3,2,2],"mantissa":[8,2,0,6,8],"miss_data":[[1,3,2,19,4,41,6,26,10,9],[2,6,5,4,14,22,11,7,1,10],[10,8,2,4,2,20,6,12,15,1],[13,2,17,3,4,6,8,3,16,9],[14,5,6,4,8,5,10,11,3,1]]},{"issue":"201810200778","lottery":["3","5","6","7","1"],"pair":[438,435],"leopard":[479,477,480],"group_three":[361,358,347],"group_six":[0,0,0],"total_val":[14,18,14,8,8],"bs_form":["011","111","110"],"oe_form":["110","101","011"],"pc_form":["110","101","010"],"other_form":["020","201","011"],"span":[3,2,6,2,6],"mantissa":[4,8,4,8,8],"miss_data":[[2,4,3,3,5,42,7,27,11,1],[3,7,6,5,15,5,12,1,2,11],[11,9,1,5,3,21,6,13,16,2],[14,3,18,1,5,7,9,7,17,10],[15,1,7,5,9,1,11,12,4,2]]},{"issue":"201810200777","lottery":["7","0","4","8","7"],"pair":[439,436],"leopard":[480,478,481],"group_three":[362,359,348],"group_six":[0,0,0],"total_val":[11,12,19,7,15],"bs_form":["100","001","011"],"oe_form":["100","000","001"],"pc_form":["100","000","001"],"other_form":["101","012","121"],"span":[7,8,4,7,1],"mantissa":[1,2,9,7,5],"miss_data":[[3,5,4,1,6,43,8,7,12,2],["0",8,7,6,16,1,13,2,3,12],[12,10,2,6,4,22,1,14,17,3],[15,4,19,2,6,8,10,1,8,11],[16,1,8,6,10,2,12,7,5,3]]},{"issue":"201810200776","lottery":["7","8","4","4","6"],"pair":[440,437],"leopard":[481,479,482],"group_three":[363,0,0],"group_six":[0,132,140],"total_val":[19,16,14,15,10],"bs_form":["110","100","001"],"oe_form":["100","000","000"],"pc_form":["100","000","000"],"other_form":["121","211","110"],"span":[4,4,2,1,2],"mantissa":[9,6,4,5,0],"miss_data":[[4,6,5,2,7,44,9,7,13,3],[1,9,8,7,17,2,14,3,8,13],[13,11,3,7,4,23,2,15,18,4],[16,5,20,3,4,9,11,2,1,12],[17,2,9,7,11,3,6,1,6,4]]},{"issue":"201810200775","lottery":["9","6","0","7","5"],"pair":[441,438],"leopard":[482,480,483],"group_three":[364,360,349],"group_six":[0,0,0],"total_val":[15,13,12,15,12],"bs_form":["110","101","011"],"oe_form":["100","001","011"],"pc_form":["000","001","011"],"other_form":["000","001","012"],"span":[9,7,7,3,2],"mantissa":[5,3,2,5,2],"miss_data":[[5,7,6,3,8,45,10,1,14,9],[2,10,9,8,18,3,6,4,1,14],["0",12,4,8,1,24,3,16,19,5],[17,6,21,4,1,10,12,7,2,13],[18,3,10,8,12,5,1,2,7,5]]},{"issue":"201810200774","lottery":["0","3","3","3","3"],"pair":[442,0],"leopard":[483,0,0],"group_three":[0,361,350],"group_six":[127,133,141],"total_val":[6,9,9,3,6],"bs_form":["000","000","000"],"oe_form":["011","111","111"],"pc_form":["011","111","111"],"other_form":["000","000","000"],"span":[3,0,0,3,0],"mantissa":[6,9,9,3,6],"miss_data":[["0",8,7,4,9,46,11,2,15,1],[3,11,10,3,19,4,1,5,2,15],[1,13,5,3,2,25,4,17,20,6],[18,7,22,3,2,11,13,1,3,14],[19,4,11,3,13,1,2,3,8,6]]},{"issue":"201810200773","lottery":["9","2","9","8","0"],"pair":[443,439],"leopard":[484,481,484],"group_three":[0,362,351],"group_six":[128,0,0],"total_val":[20,19,17,11,8],"bs_form":["101","011","110"],"oe_form":["101","010","100"],"pc_form":["010","100","000"],"other_form":["020","202","020"],"span":[7,7,9,7,8],"mantissa":[0,9,7,1,8],"miss_data":[[1,9,8,5,10,47,12,3,16,9],[4,12,2,1,20,5,2,6,3,16],[2,14,6,1,3,26,5,18,21,9],[19,8,23,1,3,12,14,2,8,15],["0",5,12,1,14,2,3,4,9,7]]},{"issue":"201810200772","lottery":["4","8","5","6","5"],"pair":[444,440],"leopard":[485,482,485],"group_three":[365,363,0],"group_six":[0,0,142],"total_val":[17,19,16,12,11],"bs_form":["011","111","111"],"oe_form":["001","010","101"],"pc_form":["001","010","101"],"other_form":["122","220","202"],"span":[4,3,1,4,1],"mantissa":[7,9,6,2,1],"miss_data":[[2,10,9,6,4,48,13,4,17,1],[5,13,1,2,21,6,3,7,8,17],[3,15,7,2,4,5,6,19,22,1],[20,9,24,2,4,13,6,3,1,16],[1,6,13,2,15,5,4,5,10,8]]},{"issue":"201810200771","lottery":["9","5","2","0","4"],"pair":[445,441],"leopard":[486,483,486],"group_three":[366,364,352],"group_six":[0,0,0],"total_val":[16,7,6,14,4],"bs_form":["110","100","000"],"oe_form":["110","100","000"],"pc_form":["011","110","100"],"other_form":["022","220","201"],"span":[7,5,4,4,4],"mantissa":[6,7,6,4,4],"miss_data":[[3,11,10,7,1,49,14,5,18,9],[6,14,2,3,22,5,4,8,1,18],[4,16,2,3,5,1,7,20,23,2],["0",10,25,3,5,14,1,4,2,17],[2,7,14,3,4,1,5,6,11,9]]},{"issue":"201810200770","lottery":["0","0","7","5","0"],"pair":[0,442],"leopard":[487,484,487],"group_three":[0,365,353],"group_six":[129,0,0],"total_val":[7,12,12,0,5],"bs_form":["001","011","110"],"oe_form":["001","011","110"],"pc_form":["001","011","110"],"other_form":["001","012","120"],"span":[7,7,7,0,5],"mantissa":[7,2,2,0,5],"miss_data":[["0",12,11,8,2,50,15,6,19,1],["0",15,3,4,23,1,5,9,2,19],[5,17,1,4,6,2,8,7,24,3],[1,11,26,4,6,5,2,5,3,18],["0",8,15,4,1,2,6,7,12,10]]},{"issue":"201810200769","lottery":["1","0","5","1","7"],"pair":[446,443],"leopard":[488,485,488],"group_three":[367,366,354],"group_six":[0,0,0],"total_val":[6,6,13,1,8],"bs_form":["001","010","101"],"oe_form":["101","011","111"],"pc_form":["001","010","101"],"other_form":["102","021","211"],"span":[5,5,6,1,6],"mantissa":[6,6,3,1,8],"miss_data":[[1,1,12,9,3,51,16,7,20,2],["0",16,4,5,24,2,6,10,3,20],[6,18,2,5,7,5,9,1,25,4],[2,1,27,5,7,1,3,6,4,19],[1,9,16,5,2,3,7,7,13,11]]},{"issue":"201810200768","lottery":["9","4","0","1","7"],"pair":[447,444],"leopard":[489,486,489],"group_three":[368,367,355],"group_six":[0,0,0],"total_val":[13,5,8,13,8],"bs_form":["100","000","001"],"oe_form":["100","001","011"],"pc_form":["000","000","001"],"other_form":["010","101","011"],"span":[9,4,7,5,6],"mantissa":[3,5,8,3,8],"miss_data":[[2,1,13,10,4,52,17,8,21,9],[1,17,5,6,4,3,7,11,4,21],["0",19,3,6,8,1,10,2,26,5],[3,1,28,6,8,2,4,7,5,20],[2,10,17,6,3,4,8,7,14,12]]},{"issue":"201810200767","lottery":["9","8","8","1","5"],"pair":[448,445],"leopard":[490,487,490],"group_three":[0,0,356],"group_six":[130,134,0],"total_val":[25,17,14,17,6],"bs_form":["111","110","101"],"oe_form":["100","001","011"],"pc_form":["000","000","001"],"other_form":["022","221","212"],"span":[1,7,7,1,4],"mantissa":[5,7,4,7,6],"miss_data":[[3,2,14,11,5,53,18,9,22,9],[2,18,6,7,1,4,8,12,8,22],[1,20,4,7,9,2,11,3,8,6],[4,1,29,7,9,3,5,8,6,21],[3,11,18,7,4,5,9,1,15,13]]},{"issue":"201810200766","lottery":["7","1","2","9","8"],"pair":[449,446],"leopard":[491,488,491],"group_three":[369,368,357],"group_six":[0,0,0],"total_val":[10,12,19,8,17],"bs_form":["100","001","011"],"oe_form":["110","101","010"],"pc_form":["101","010","100"],"other_form":["112","120","202"],"span":[6,8,7,6,1],"mantissa":[0,2,9,8,7],"miss_data":[[4,3,15,12,6,54,19,7,23,1],[3,1,7,8,2,5,9,13,1,23],[2,21,2,8,10,3,12,4,1,7],[5,1,30,8,10,4,6,9,7,9],[4,12,19,8,5,1,10,2,8,14]]},{"issue":"201810200765","lottery":["6","4","1","2","6"],"pair":[450,447],"leopard":[492,489,492],"group_three":[370,369,358],"group_six":[0,0,0],"total_val":[11,7,9,10,8],"bs_form":["100","000","001"],"oe_form":["001","010","100"],"pc_form":["000","001","010"],"other_form":["011","112","120"],"span":[5,3,5,2,4],"mantissa":[1,7,9,0,8],"miss_data":[[5,4,16,13,7,55,6,1,24,2],[4,1,8,9,4,6,10,14,2,24],[3,1,1,9,11,4,13,5,2,8],[6,2,2,9,11,5,7,10,8,1],[5,13,20,9,6,2,6,3,1,15]]},{"issue":"201810200764","lottery":["8","7","8","6","6"],"pair":[451,0],"leopard":[493,490,493],"group_three":[0,370,0],"group_six":[131,0,143],"total_val":[23,21,20,15,12],"bs_form":["111","111","111"],"oe_form":["010","100","000"],"pc_form":["010","100","000"],"other_form":["212","120","200"],"span":[1,2,2,1,0],"mantissa":[3,1,0,5,2],"miss_data":[[6,5,17,14,8,56,1,2,8,3],[5,2,9,10,1,7,11,7,3,25],[4,1,2,10,12,5,14,6,8,9],[7,3,1,10,12,6,6,11,9,2],[6,14,21,10,7,3,6,4,2,16]]},{"issue":"201810200763","lottery":["5","5","1","6","3"],"pair":[0,448],"leopard":[494,491,494],"group_three":[0,371,359],"group_six":[132,0,0],"total_val":[11,12,10,10,9],"bs_form":["110","101","010"],"oe_form":["111","110","101"],"pc_form":["110","100","001"],"other_form":["221","210","100"],"span":[4,5,5,0,3],"mantissa":[1,2,0,0,9],"miss_data":[[7,6,18,15,9,5,2,3,1,4],[6,3,10,11,2,5,12,1,4,26],[5,1,3,11,13,6,15,7,1,10],[8,4,2,11,13,7,6,12,10,3],[7,15,22,3,8,4,1,5,3,17]]},{"issue":"201810200762","lottery":["0","9","0","8","7"],"pair":[452,449],"leopard":[495,492,495],"group_three":[0,372,360],"group_six":[133,0,0],"total_val":[9,17,15,9,15],"bs_form":["010","101","011"],"oe_form":["010","100","001"],"pc_form":["000","000","001"],"other_form":["000","002","021"],"span":[9,9,8,9,1],"mantissa":[9,7,5,9,5],"miss_data":[["0",7,19,16,10,1,3,4,2,5],[7,4,11,12,3,1,13,2,5,9],["0",1,4,12,14,7,16,8,2,11],[9,5,3,12,14,8,1,13,8,4],[8,16,23,1,9,5,2,7,4,18]]},{"issue":"201810200761","lottery":["2","3","5","1","2"],"pair":[453,450],"leopard":[496,493,496],"group_three":[371,373,361],"group_six":[0,0,0],"total_val":[10,9,8,5,3],"bs_form":["001","010","100"],"oe_form":["011","111","110"],"pc_form":["111","110","101"],"other_form":["202","021","212"],"span":[3,4,4,1,1],"mantissa":[0,9,8,5,3],"miss_data":[[1,8,2,17,11,2,4,5,3,6],[8,5,12,3,4,2,14,3,6,1],[1,2,5,13,15,5,17,9,3,12],[10,1,4,13,15,9,2,14,1,5],[9,17,2,2,10,6,3,1,5,19]]},{"issue":"201810200760","lottery":["9","1","5","7","8"],"pair":[454,451],"leopard":[497,494,497],"group_three":[372,374,362],"group_six":[0,0,0],"total_val":[15,13,20,10,15],"bs_form":["101","011","111"],"oe_form":["111","111","110"],"pc_form":["001","011","110"],"other_form":["012","121","212"],"span":[8,6,3,8,1],"mantissa":[5,3,0,0,5],"miss_data":[[2,9,1,18,12,3,5,6,4,9],[9,1,13,1,5,3,15,4,7,2],[2,3,6,14,16,5,18,10,4,13],[11,1,5,14,16,10,3,7,2,6],[10,18,1,3,11,7,4,2,8,20]]},{"issue":"201810200759","lottery":["8","1","9","1","3"],"pair":[455,452],"leopard":[498,495,498],"group_three":[373,0,363],"group_six":[0,135,0],"total_val":[18,11,13,9,4],"bs_form":["101","010","100"],"oe_form":["011","111","111"],"pc_form":["000","000","001"],"other_form":["210","101","010"],"span":[8,8,8,7,2],"mantissa":[8,1,3,9,4],"miss_data":[[3,10,2,19,13,4,6,7,8,1],[10,1,14,2,6,4,16,5,8,3],[3,4,7,15,17,1,19,11,5,9],[12,1,6,15,17,11,4,1,3,7],[11,19,2,3,12,8,5,3,1,21]]},{"issue":"201810200758","lottery":["2","7","6","0","0"],"pair":[456,0],"leopard":[499,496,499],"group_three":[374,375,0],"group_six":[0,0,144],"total_val":[15,13,6,9,0],"bs_form":["011","110","100"],"oe_form":["010","100","000"],"pc_form":["110","100","000"],"other_form":["210","100","000"],"span":[5,7,6,5,0],"mantissa":[5,3,6,9,0],"miss_data":[[4,11,2,20,14,5,7,8,1,2],[11,1,15,3,7,5,17,7,9,4],[4,5,8,16,18,2,6,12,6,1],["0",1,7,16,18,12,5,2,4,8],["0",20,3,1,13,9,6,4,2,22]]},{"issue":"201810200757","lottery":["9","2","5","0","2"],"pair":[457,453],"leopard":[500,497,500],"group_three":[375,376,364],"group_six":[0,0,0],"total_val":[16,7,7,11,2],"bs_form":["101","010","100"],"oe_form":["101","010","100"],"pc_form":["011","110","101"],"other_form":["022","220","202"],"span":[7,5,5,7,2],"mantissa":[6,7,7,1,2],"miss_data":[[5,12,1,21,15,6,8,9,2,9],[12,2,2,4,8,6,18,1,10,5],[5,6,9,17,19,5,1,13,7,2],["0",2,8,17,19,13,6,3,5,9],[1,21,2,2,14,10,7,5,3,23]]},{"issue":"201810200756","lottery":["6","2","8","3","7"],"pair":[458,454],"leopard":[501,498,501],"group_three":[376,377,365],"group_six":[0,0,0],"total_val":[16,13,18,8,10],"bs_form":["101","010","101"],"oe_form":["000","001","011"],"pc_form":["010","101","011"],"other_form":["022","220","201"],"span":[6,6,5,4,4],"mantissa":[6,3,8,8,0],"miss_data":[[6,13,2,22,16,7,6,10,3,1],[13,3,2,5,9,7,19,2,11,6],[6,7,10,18,20,1,2,14,8,3],[1,3,9,3,20,14,7,4,6,10],[2,22,1,3,15,11,8,7,4,24]]},{"issue":"201810200755","lottery":["1","4","4","0","1"],"pair":[459,455],"leopard":[502,499,502],"group_three":[0,0,366],"group_six":[134,136,0],"total_val":[9,8,5,5,1],"bs_form":["000","000","000"],"oe_form":["100","000","001"],"pc_form":["000","000","000"],"other_form":["111","110","101"],"span":[3,4,4,3,1],"mantissa":[9,8,5,5,1],"miss_data":[[7,1,3,23,17,8,1,11,4,2],[14,4,1,6,4,8,20,3,12,7],[7,8,11,19,4,2,3,15,1,4],["0",4,10,1,21,15,8,5,7,11],[3,1,2,4,16,12,9,1,5,25]]},{"issue":"201810200754","lottery":["1","2","6","8","9"],"pair":[460,456],"leopard":[503,500,503],"group_three":[377,378,367],"group_six":[0,0,0],"total_val":[9,16,23,3,17],"bs_form":["001","011","111"],"oe_form":["100","000","001"],"pc_form":["010","100","000"],"other_form":["120","202","020"],"span":[5,6,3,1,1],"mantissa":[9,6,3,3,7],"miss_data":[[8,1,4,24,18,9,2,12,5,3],[15,5,2,7,1,9,21,4,13,8],[8,9,12,20,1,3,6,16,2,5],[1,5,11,2,22,16,9,6,8,12],[4,1,3,5,17,13,10,2,6,9]]},{"issue":"201810200753","lottery":["8","9","7","6","4"],"pair":[461,457],"leopard":[504,501,504],"group_three":[378,379,368],"group_six":[0,0,0],"total_val":[24,22,17,17,10],"bs_form":["111","111","110"],"oe_form":["011","110","100"],"pc_form":["001","010","100"],"other_form":["201","010","101"],"span":[2,3,3,1,2],"mantissa":[4,2,7,7,0],"miss_data":[[9,1,5,25,19,10,3,13,8,4],[16,6,1,8,2,10,22,5,14,9],[9,10,13,21,2,4,1,7,3,6],[2,6,12,3,23,17,6,7,1,13],[5,2,4,6,4,14,11,3,7,1]]},{"issue":"201810200752","lottery":["4","6","1","2","8"],"pair":[462,458],"leopard":[505,502,505],"group_three":[379,380,369],"group_six":[0,0,0],"total_val":[11,9,11,10,10],"bs_form":["010","100","001"],"oe_form":["001","010","100"],"pc_form":["000","001","010"],"other_form":["101","012","122"],"span":[5,5,7,2,6],"mantissa":[1,9,1,0,0],"miss_data":[[10,2,6,26,4,11,4,14,1,5],[17,7,2,9,3,11,6,6,15,1],[10,1,14,22,3,5,2,1,4,7],[3,7,2,4,24,18,1,8,2,14],[6,3,5,7,1,15,12,4,8,2]]},{"issue":"201810200751","lottery":["4","2","9","0","5"],"pair":[463,459],"leopard":[506,503,506],"group_three":[380,381,370],"group_six":[0,0,0],"total_val":[15,11,14,6,5],"bs_form":["001","010","101"],"oe_form":["001","010","101"],"pc_form":["010","100","001"],"other_form":["120","200","002"],"span":[7,9,9,2,5],"mantissa":[5,1,4,6,5],"miss_data":[[11,3,7,27,4,12,5,15,2,6],[18,8,2,10,4,12,1,7,16,2],[11,1,15,23,4,6,3,2,5,9],["0",8,1,5,25,19,2,9,3,15],[7,4,6,8,2,5,13,5,1,3]]},{"issue":"201810200750","lottery":["3","9","0","3","1"],"pair":[464,460],"leopard":[507,504,507],"group_three":[381,382,371],"group_six":[0,0,0],"total_val":[12,12,4,12,4],"bs_form":["010","100","000"],"oe_form":["110","101","011"],"pc_form":["100","001","010"],"other_form":["000","000","001"],"span":[9,9,3,6,2],"mantissa":[2,2,4,2,4],"miss_data":[[12,4,8,3,1,13,6,16,3,7],[19,9,1,11,5,13,2,8,17,9],["0",2,16,24,5,7,4,3,6,1],[1,9,2,3,26,20,3,10,4,16],[8,1,7,9,3,1,14,6,2,4]]},{"issue":"201810200749","lottery":["9","0","8","6","3"],"pair":[465,461],"leopard":[508,505,508],"group_three":[382,383,372],"group_six":[0,0,0],"total_val":[17,14,17,9,9],"bs_form":["101","011","110"],"oe_form":["100","000","001"],"pc_form":["000","000","001"],"other_form":["002","020","200"],"span":[9,8,5,9,3],"mantissa":[7,4,7,9,9],"miss_data":[[13,5,9,1,2,14,7,17,4,9],["0",10,2,12,6,14,3,9,18,1],[1,3,17,25,6,8,5,4,8,2],[2,10,3,1,27,21,6,11,5,17],[9,1,8,3,4,2,15,7,3,5]]},{"issue":"201810200748","lottery":["7","5","0","6","1"],"pair":[466,462],"leopard":[509,506,509],"group_three":[383,384,373],"group_six":[0,0,0],"total_val":[12,11,7,12,7],"bs_form":["110","101","010"],"oe_form":["110","100","001"],"pc_form":["110","100","000"],"other_form":["120","200","001"],"span":[7,6,6,2,5],"mantissa":[2,1,7,2,7],"miss_data":[[14,6,10,2,3,15,8,7,5,1],[1,11,3,13,7,5,4,10,19,2],["0",4,18,26,7,9,6,5,1,3],[3,11,4,2,28,22,6,12,6,18],[10,1,9,1,5,3,16,8,4,6]]},{"issue":"201810200747","lottery":["3","3","0","9","3"],"pair":[0,463],"leopard":[510,507,510],"group_three":[0,385,374],"group_six":[135,0,0],"total_val":[6,12,12,6,12],"bs_form":["000","001","010"],"oe_form":["110","101","011"],"pc_form":["110","100","001"],"other_form":["000","000","000"],"span":[3,9,9,0,6],"mantissa":[6,2,2,6,2],"miss_data":[[15,7,11,3,4,16,9,1,6,2],[2,12,4,3,8,1,5,11,20,3],["0",5,19,27,8,10,7,6,2,4],[4,12,5,3,29,23,1,13,7,9],[11,1,10,3,6,4,17,9,5,7]]},{"issue":"201810200746","lottery":["6","4","7","9","4"],"pair":[467,464],"leopard":[511,508,511],"group_three":[384,386,375],"group_six":[0,0,0],"total_val":[17,20,20,10,13],"bs_form":["101","011","110"],"oe_form":["001","011","110"],"pc_form":["001","010","100"],"other_form":["011","110","101"],"span":[3,5,5,2,5],"mantissa":[7,0,0,0,3],"miss_data":[[16,8,12,1,5,17,6,2,7,3],[3,13,5,1,4,2,6,12,21,4],[1,6,20,28,9,11,8,7,3,5],[5,13,6,4,30,24,2,14,8,9],[12,2,11,1,4,5,18,10,6,8]]},{"issue":"201810200745","lottery":["2","0","3","5","5"],"pair":[468,0],"leopard":[512,509,512],"group_three":[385,387,0],"group_six":[0,0,145],"total_val":[5,8,13,2,10],"bs_form":["000","001","011"],"oe_form":["001","011","111"],"pc_form":["101","011","111"],"other_form":["200","002","022"],"span":[3,5,2,2,0],"mantissa":[5,8,3,2,0],"miss_data":[[17,9,2,2,6,18,1,3,8,4],["0",14,6,2,1,3,7,13,22,5],[2,7,21,3,10,12,9,1,4,6],[6,14,7,5,31,5,3,15,9,1],[13,3,12,2,1,5,19,11,7,9]]},{"issue":"201810200744","lottery":["0","3","8","2","1"],"pair":[469,465],"leopard":[513,510,513],"group_three":[386,388,376],"group_six":[0,0,0],"total_val":[11,13,11,3,3],"bs_form":["001","010","100"],"oe_form":["010","100","001"],"pc_form":["010","101","010"],"other_form":["002","022","221"],"span":[8,6,7,3,1],"mantissa":[1,3,1,3,3],"miss_data":[["0",10,1,3,7,19,2,4,9,5],[1,15,7,3,2,4,8,14,23,6],[3,8,22,1,11,13,10,2,8,7],[7,15,2,6,32,1,4,16,10,2],[14,1,13,3,2,1,20,12,8,10]]},{"issue":"201810200743","lottery":["7","8","9","6","5"],"pair":[470,466],"leopard":[514,511,514],"group_three":[387,389,377],"group_six":[0,0,0],"total_val":[24,23,20,15,11],"bs_form":["111","111","111"],"oe_form":["101","010","101"],"pc_form":["100","000","001"],"other_form":["120","200","002"],"span":[2,3,4,1,1],"mantissa":[4,3,0,5,1],"miss_data":[[1,11,2,4,8,20,3,7,10,6],[2,16,8,1,3,5,9,15,8,7],[4,9,23,2,12,14,11,3,1,9],[8,16,1,7,33,2,6,17,11,3],[15,1,14,4,3,5,21,13,9,11]]},{"issue":"201810200742","lottery":["9","2","9","7","7"],"pair":[471,0],"leopard":[515,512,515],"group_three":[0,390,0],"group_six":[136,0,146],"total_val":[20,18,23,11,14],"bs_form":["101","011","111"],"oe_form":["101","011","111"],"pc_form":["010","101","011"],"other_form":["020","201","011"],"span":[7,7,2,7,0],"mantissa":[0,8,3,1,4],"miss_data":[[2,12,3,5,9,21,4,1,11,9],[3,17,2,2,4,6,10,16,1,8],[5,10,24,3,13,15,12,4,2,9],[9,17,2,8,34,3,1,7,12,4],[16,2,15,5,4,1,22,7,10,12]]},{"issue":"201810200741","lottery":["6","2","7","8","3"],"pair":[472,467],"leopard":[516,513,516],"group_three":[388,391,378],"group_six":[0,0,0],"total_val":[15,17,18,8,11],"bs_form":["101","011","110"],"oe_form":["001","010","101"],"pc_form":["011","110","101"],"other_form":["021","212","120"],"span":[5,6,5,4,5],"mantissa":[5,7,8,8,1],"miss_data":[[3,13,4,6,10,22,6,2,12,1],[4,18,2,3,5,7,11,17,2,9],[6,11,25,4,14,16,13,7,3,1],[10,18,3,9,35,4,2,1,8,5],[17,3,16,3,5,2,23,1,11,13]]},{"issue":"201810200740","lottery":["8","5","8","9","9"],"pair":[473,0],"leopard":[517,514,517],"group_three":[0,392,0],"group_six":[137,0,147],"total_val":[21,22,26,13,18],"bs_form":["111","111","111"],"oe_form":["010","101","011"],"pc_form":["010","100","000"],"other_form":["222","220","200"],"span":[3,4,1,3,0],"mantissa":[1,2,6,3,8],"miss_data":[[4,14,5,7,11,23,1,3,8,2],[5,19,1,4,6,5,12,18,3,10],[7,12,26,5,15,17,14,1,8,2],[11,19,4,10,36,5,3,2,1,9],[18,4,17,1,6,3,24,2,12,9]]},{"issue":"201810200739","lottery":["0","9","3","6","0"],"pair":[474,468],"leopard":[518,515,518],"group_three":[389,393,379],"group_six":[0,0,0],"total_val":[12,18,9,9,6],"bs_form":["010","101","010"],"oe_form":["011","110","100"],"pc_form":["001","010","100"],"other_form":["000","000","000"],"span":[9,6,6,9,6],"mantissa":[2,8,9,9,6],"miss_data":[["0",15,6,8,12,24,2,4,1,3],[6,20,2,5,7,1,13,19,4,9],[8,13,27,3,16,18,15,2,1,3],[12,20,5,11,37,6,6,3,2,1],["0",5,18,2,7,4,25,3,13,1]]},{"issue":"201810200738","lottery":["7","4","7","2","8"],"pair":[475,469],"leopard":[519,516,519],"group_three":[0,394,380],"group_six":[138,0,0],"total_val":[18,13,17,11,10],"bs_form":["101","010","101"],"oe_form":["101","010","100"],"pc_form":["101","011","110"],"other_form":["111","112","122"],"span":[3,5,6,3,6],"mantissa":[8,3,7,1,0],"miss_data":[[1,16,7,9,13,25,3,7,2,4],[7,21,3,6,4,2,14,20,5,1],[9,14,28,1,17,19,16,7,2,4],[13,21,2,12,38,7,1,4,3,2],[1,6,19,3,8,5,26,4,8,2]]},{"issue":"201810200737","lottery":["4","6","4","8","7"],"pair":[476,470],"leopard":[520,517,520],"group_three":[0,395,381],"group_six":[139,0,0],"total_val":[14,18,19,10,15],"bs_form":["010","101","011"],"oe_form":["000","000","001"],"pc_form":["000","000","001"],"other_form":["101","012","121"],"span":[2,4,4,2,1],"mantissa":[4,8,9,0,5],"miss_data":[[2,17,8,10,4,26,4,1,3,5],[8,22,4,7,1,3,6,21,6,2],[10,15,29,2,4,20,17,1,3,5],[14,22,1,13,39,8,2,5,8,3],[2,7,20,4,9,6,27,7,1,3]]},{"issue":"201810200736","lottery":["6","7","0","5","2"],"pair":[477,471],"leopard":[521,518,521],"group_three":[390,396,382],"group_six":[0,0,0],"total_val":[13,12,7,13,7],"bs_form":["110","101","010"],"oe_form":["010","101","010"],"pc_form":["010","101","011"],"other_form":["010","102","022"],"span":[7,7,5,1,3],"mantissa":[3,2,7,3,7],"miss_data":[[3,18,9,11,1,27,6,2,4,6],[9,23,5,8,2,4,1,7,7,3],["0",16,30,3,1,21,18,2,4,6],[15,23,2,14,40,5,3,6,1,4],[3,8,2,5,10,7,28,1,2,4]]},{"issue":"201810200735","lottery":["3","4","3","4","5"],"pair":[478,472],"leopard":[522,519,522],"group_three":[0,0,383],"group_six":[140,137,0],"total_val":[10,11,12,7,9],"bs_form":["000","000","001"],"oe_form":["101","010","101"],"pc_form":["101","010","101"],"other_form":["010","101","012"],"span":[1,1,2,1,1],"mantissa":[0,1,2,7,9],"miss_data":[[4,19,10,3,2,28,1,3,5,7],[10,24,6,9,4,5,2,1,8,4],[1,17,31,3,2,22,19,3,5,7],[16,24,3,15,4,1,4,7,2,5],[4,9,1,6,11,5,29,2,3,5]]},{"issue":"201810200734","lottery":["1","8","3","1","9"],"pair":[479,473],"leopard":[523,520,523],"group_three":[391,397,384],"group_six":[0,0,0],"total_val":[12,12,13,9,10],"bs_form":["010","100","001"],"oe_form":["101","011","111"],"pc_form":["001","010","100"],"other_form":["120","201","010"],"span":[7,7,8,7,8],"mantissa":[2,2,3,9,0],"miss_data":[[5,1,11,1,3,29,2,4,6,8],[11,25,7,10,1,6,3,2,8,5],[2,18,32,3,3,23,20,4,6,8],[17,1,4,16,1,2,5,8,3,6],[5,10,2,7,12,1,30,3,4,9]]},{"issue":"201810200733","lottery":["2","7","7","1","4"],"pair":[480,474],"leopard":[524,521,524],"group_three":[0,0,385],"group_six":[141,138,0],"total_val":[16,15,12,9,5],"bs_form":["011","110","100"],"oe_form":["011","111","110"],"pc_form":["111","110","100"],"other_form":["211","111","111"],"span":[5,6,6,5,3],"mantissa":[6,5,2,9,5],"miss_data":[[6,1,2,2,4,30,3,5,7,9],[12,26,8,11,2,7,4,7,1,6],[3,19,33,1,4,24,21,7,7,9],[18,1,5,17,2,3,6,9,4,7],[6,11,3,8,4,2,31,4,5,1]]},{"issue":"201810200732","lottery":["4","1","3","4","8"],"pair":[481,475],"leopard":[525,522,525],"group_three":[392,398,386],"group_six":[0,0,0],"total_val":[8,8,15,5,12],"bs_form":["000","000","001"],"oe_form":["011","110","100"],"pc_form":["001","010","100"],"other_form":["110","101","012"],"span":[3,3,5,3,4],"mantissa":[8,8,5,5,2],"miss_data":[[7,2,1,3,4,31,4,6,8,10],[13,1,9,12,3,8,5,1,2,7],[4,20,34,3,5,25,22,1,8,10],[19,1,6,18,4,4,7,10,5,8],[7,12,4,9,1,3,32,5,8,2]]},{"issue":"201810200731","lottery":["3","6","1","0","9"],"pair":[482,476],"leopard":[526,523,526],"group_three":[393,399,387],"group_six":[0,0,0],"total_val":[10,7,10,9,9],"bs_form":["010","100","001"],"oe_form":["101","010","101"],"pc_form":["100","000","000"],"other_form":["001","010","100"],"span":[5,6,9,3,9],"mantissa":[0,7,0,9,9],"miss_data":[[8,3,2,3,1,32,5,7,9,11],[14,1,10,13,4,9,6,2,3,8],[5,1,35,1,6,26,23,2,9,11],["0",2,7,19,1,5,8,11,6,9],[8,13,5,10,2,4,33,6,1,9]]},{"issue":"201810200730","lottery":["8","1","0","0","4"],"pair":[483,477],"leopard":[527,524,527],"group_three":[394,0,0],"group_six":[0,139,148],"total_val":[9,1,4,9,4],"bs_form":["100","000","000"],"oe_form":["010","100","000"],"pc_form":["000","000","000"],"other_form":["210","100","001"],"span":[8,1,4,7,4],"mantissa":[9,1,4,9,4],"miss_data":[[9,4,3,1,2,33,6,8,8,12],[15,1,11,14,5,10,1,3,4,9],["0",1,36,2,7,27,24,3,10,12],["0",3,8,20,2,6,9,12,7,10],[9,14,6,11,4,5,34,7,2,1]]},{"issue":"201810200729","lottery":["2","7","9","9","1"],"pair":[484,478],"leopard":[528,525,528],"group_three":[395,0,0],"group_six":[0,140,149],"total_val":[18,25,19,9,10],"bs_form":["011","111","110"],"oe_form":["011","111","111"],"pc_form":["110","100","000"],"other_form":["210","100","001"],"span":[7,2,8,5,8],"mantissa":[8,5,9,9,0],"miss_data":[[10,5,2,2,3,34,7,9,1,13],[16,1,12,15,6,11,2,7,5,10],[1,2,37,3,8,28,25,4,11,9],[1,4,9,21,3,7,10,13,8,9],[10,1,7,12,1,6,35,8,3,2]]},{"issue":"201810200728","lottery":["4","5","9","7","7"],"pair":[485,0],"leopard":[529,526,529],"group_three":[396,400,0],"group_six":[0,0,150],"total_val":[18,21,23,9,14],"bs_form":["011","111","111"],"oe_form":["011","111","111"],"pc_form":["010","101","011"],"other_form":["120","201","011"],"span":[5,4,2,1,0],"mantissa":[8,1,3,9,4],"miss_data":[[11,6,1,3,4,35,8,10,2,14],[17,2,13,16,7,5,3,1,6,11],[2,3,38,4,9,29,26,5,12,9],[2,5,10,22,4,8,11,7,9,1],[11,1,8,13,2,7,36,7,4,3]]},{"issue":"201810200727","lottery":["7","2","3","6","9"],"pair":[486,479],"leopard":[530,527,530],"group_three":[397,401,388],"group_six":[0,0,0],"total_val":[12,11,18,9,15],"bs_form":["100","001","011"],"oe_form":["101","010","101"],"pc_form":["111","110","100"],"other_form":["120","200","000"],"span":[5,4,6,5,3],"mantissa":[2,1,8,9,5],"miss_data":[[12,7,2,4,1,36,9,7,3,15],[18,3,2,17,8,1,4,2,7,12],[3,4,39,3,10,30,27,6,13,1],[3,6,11,23,5,9,6,1,10,2],[12,2,9,14,3,8,37,1,5,9]]},{"issue":"201810200726","lottery":["5","8","4","2","0"],"pair":[487,480],"leopard":[531,528,531],"group_three":[398,402,389],"group_six":[0,0,0],"total_val":[17,14,6,13,2],"bs_form":["110","100","000"],"oe_form":["100","000","000"],"pc_form":["100","001","010"],"other_form":["221","212","120"],"span":[4,6,4,3,2],"mantissa":[7,4,6,3,2],"miss_data":[[13,8,3,5,2,5,10,1,4,16],[19,4,1,18,9,2,5,3,8,13],[4,5,40,1,4,31,28,7,14,2],[4,7,2,24,6,10,1,2,11,3],["0",3,10,15,4,9,38,2,6,1]]},{"issue":"201810200725","lottery":["8","8","5","4","8"],"pair":[0,481],"leopard":[532,529,532],"group_three":[0,403,390],"group_six":[142,0,0],"total_val":[21,17,17,16,12],"bs_form":["111","110","101"],"oe_form":["001","010","100"],"pc_form":["001","010","100"],"other_form":["222","221","212"],"span":[3,4,4,0,4],"mantissa":[1,7,7,6,2],"miss_data":[[14,9,4,6,3,1,11,2,8,17],[20,5,2,19,10,3,6,4,8,14],[5,6,41,2,1,5,29,8,15,3],[5,8,1,25,4,11,2,3,12,4],[1,4,11,16,5,10,39,3,8,2]]},{"issue":"201810200724","lottery":["7","0","4","3","3"],"pair":[488,0],"leopard":[533,530,533],"group_three":[399,404,0],"group_six":[0,0,151],"total_val":[11,7,10,7,6],"bs_form":["100","000","000"],"oe_form":["100","001","011"],"pc_form":["100","001","011"],"other_form":["101","010","100"],"span":[7,4,1,7,0],"mantissa":[1,7,0,7,6],"miss_data":[[15,10,5,7,4,2,12,7,1,18],["0",6,3,20,11,4,7,5,1,15],[6,7,42,3,4,1,30,9,16,4],[6,9,2,3,1,12,3,4,13,5],[2,5,12,3,6,11,40,4,1,3]]},{"issue":"201810200723","lottery":["5","3","7","5","7"],"pair":[489,482],"leopard":[534,531,534],"group_three":[400,405,0],"group_six":[0,0,152],"total_val":[15,15,19,8,12],"bs_form":["101","011","111"],"oe_form":["111","111","111"],"pc_form":["111","111","111"],"other_form":["201","012","121"],"span":[4,4,2,2,2],"mantissa":[5,5,9,8,2],"miss_data":[[16,11,6,8,5,5,13,1,2,19],[1,7,4,3,12,5,8,6,2,16],[7,8,43,4,1,2,31,7,17,5],[7,10,3,1,2,5,4,5,14,6],[3,6,13,1,7,12,41,7,2,4]]},{"issue":"201810200722","lottery":["1","0","8","0","5"],"pair":[490,483],"leopard":[535,532,535],"group_three":[401,0,391],"group_six":[0,141,0],"total_val":[9,8,13,1,5],"bs_form":["001","010","101"],"oe_form":["100","000","001"],"pc_form":["000","000","001"],"other_form":["102","020","202"],"span":[8,8,8,1,5],"mantissa":[9,8,3,1,5],"miss_data":[[17,1,7,9,6,1,14,2,3,20],["0",8,5,1,13,6,9,7,3,17],[8,9,44,5,2,3,32,1,8,6],["0",11,4,2,3,1,5,6,15,7],[4,7,14,2,8,5,42,1,3,5]]},{"issue":"201810200721","lottery":["1","0","0","1","1"],"pair":[491,0],"leopard":[536,533,536],"group_three":[0,0,0],"group_six":[143,142,153],"total_val":[1,1,2,1,2],"bs_form":["000","000","000"],"oe_form":["100","001","011"],"pc_form":["000","000","000"],"other_form":["100","001","011"],"span":[1,1,1,1,0],"mantissa":[1,1,2,1,2],"miss_data":[[18,1,8,10,7,2,15,3,4,21],["0",9,6,2,14,7,10,8,4,18],["0",10,45,6,3,4,33,2,1,7],[1,1,5,3,4,2,6,7,16,8],[5,1,15,3,9,1,43,2,4,6]]},{"issue":"201810200720","lottery":["1","9","5","5","6"],"pair":[492,484],"leopard":[537,534,537],"group_three":[402,0,0],"group_six":[0,143,154],"total_val":[15,19,16,10,11],"bs_form":["011","111","111"],"oe_form":["111","111","110"],"pc_form":["001","011","110"],"other_form":["102","022","220"],"span":[8,4,1,8,1],"mantissa":[5,9,6,0,1],"miss_data":[[19,1,9,11,8,3,16,4,5,22],[1,10,7,3,15,8,11,9,5,9],[1,11,46,7,4,5,34,3,2,8],[2,1,6,4,5,5,7,8,17,9],[6,1,16,4,10,2,6,3,5,7]]},{"issue":"201810200719","lottery":["1","8","4","7","2"],"pair":[493,485],"leopard":[538,535,538],"group_three":[403,406,392],"group_six":[0,0,0],"total_val":[13,19,13,9,9],"bs_form":["010","101","010"],"oe_form":["100","001","010"],"pc_form":["000","001","011"],"other_form":["121","211","112"],"span":[7,4,5,7,5],"mantissa":[3,9,3,9,9],"miss_data":[[20,1,10,12,9,4,17,5,6,23],[2,11,8,4,16,9,12,10,8,1],[2,12,47,8,4,1,35,4,3,9],[3,2,7,5,6,1,8,7,18,10],[7,2,2,5,11,3,1,4,6,8]]},{"issue":"201810200718","lottery":["3","0","4","9","9"],"pair":[494,0],"leopard":[539,536,539],"group_three":[404,407,0],"group_six":[0,0,155],"total_val":[7,13,22,3,18],"bs_form":["000","001","011"],"oe_form":["100","001","011"],"pc_form":["100","000","000"],"other_form":["001","010","100"],"span":[4,9,5,3,0],"mantissa":[7,3,2,3,8],"miss_data":[[21,1,11,3,10,5,18,6,7,24],["0",12,9,5,17,10,13,11,1,2],[3,13,48,9,4,2,36,5,4,10],[4,3,8,6,7,2,9,1,19,9],[8,3,1,6,12,4,2,5,7,9]]},{"issue":"201810200717","lottery":["3","1","4","8","9"],"pair":[495,486],"leopard":[540,537,540],"group_three":[405,408,393],"group_six":[0,0,0],"total_val":[8,13,21,4,17],"bs_form":["000","001","011"],"oe_form":["110","100","001"],"pc_form":["100","000","000"],"other_form":["011","112","120"],"span":[3,7,5,2,1],"mantissa":[8,3,1,4,7],"miss_data":[[22,2,12,3,11,6,19,7,8,25],[1,1,10,6,18,11,14,12,2,3],[4,14,49,10,4,3,37,6,5,11],[5,4,9,7,8,3,10,2,8,1],[9,4,2,7,13,5,3,6,8,9]]},{"issue":"201810200716","lottery":["1","6","1","0","0"],"pair":[496,0],"leopard":[541,538,541],"group_three":[0,409,0],"group_six":[144,0,156],"total_val":[8,7,1,7,0],"bs_form":["010","100","000"],"oe_form":["101","010","100"],"pc_form":["000","000","000"],"other_form":["101","010","100"],"span":[5,6,1,5,0],"mantissa":[8,7,1,7,0],"miss_data":[[23,1,13,1,12,7,20,8,9,26],[2,1,11,7,19,12,6,13,3,4],[5,1,50,11,1,4,38,7,6,12],["0",5,10,8,9,4,11,3,1,2],["0",5,3,8,14,6,4,7,9,1]]},{"issue":"201810200715","lottery":["6","7","3","9","4"],"pair":[497,487],"leopard":[542,539,542],"group_three":[406,410,394],"group_six":[0,0,0],"total_val":[16,19,16,13,13],"bs_form":["110","101","010"],"oe_form":["011","111","110"],"pc_form":["011","110","100"],"other_form":["010","100","001"],"span":[4,6,6,1,5],"mantissa":[6,9,6,3,3],"miss_data":[[24,1,14,2,13,8,6,9,10,27],[3,2,12,8,20,13,1,7,4,5],[6,1,51,3,2,5,39,8,7,13],[1,6,11,9,10,5,12,4,2,9],[1,6,4,9,4,7,5,8,10,2]]},{"issue":"201810200714","lottery":["6","9","4","8","7"],"pair":[498,488],"leopard":[543,540,543],"group_three":[407,411,395],"group_six":[0,0,0],"total_val":[19,21,19,15,15],"bs_form":["110","101","011"],"oe_form":["010","100","001"],"pc_form":["000","000","001"],"other_form":["001","012","121"],"span":[5,5,4,3,1],"mantissa":[9,1,9,5,5],"miss_data":[[25,2,15,3,14,9,6,10,11,28],[4,3,13,9,21,14,2,1,5,9],[7,2,52,1,4,6,40,9,8,14],[2,7,12,10,11,6,13,5,8,1],[2,7,5,10,1,8,6,7,11,3]]},{"issue":"201810200713","lottery":["3","6","8","3","6"],"pair":[499,489],"leopard":[544,541,544],"group_three":[408,412,396],"group_six":[0,0,0],"total_val":[17,17,17,9,9],"bs_form":["011","110","101"],"oe_form":["100","001","010"],"pc_form":["100","001","010"],"other_form":["002","020","200"],"span":[5,5,5,3,3],"mantissa":[7,7,7,9,9],"miss_data":[[26,3,16,3,15,10,1,11,12,29],[5,4,14,10,22,15,6,2,6,1],[8,3,53,2,1,7,41,10,8,15],[3,8,13,3,12,7,14,6,1,2],[3,8,6,11,2,9,6,1,12,4]]},{"issue":"201810200712","lottery":["8","6","7","0","1"],"pair":[500,490],"leopard":[545,542,545],"group_three":[409,413,397],"group_six":[0,0,0],"total_val":[21,13,8,14,1],"bs_form":["111","110","100"],"oe_form":["001","010","101"],"pc_form":["001","010","100"],"other_form":["201","010","101"],"span":[2,7,7,2,1],"mantissa":[1,3,8,4,1],"miss_data":[[27,4,17,1,16,11,2,12,8,30],[6,5,15,11,23,16,6,3,7,2],[9,4,54,3,2,8,42,7,1,16],["0",9,14,1,13,8,15,7,2,3],[4,1,7,12,3,10,1,2,13,5]]},{"issue":"201810200711","lottery":["8","1","4","0","6"],"pair":[501,491],"leopard":[546,543,546],"group_three":[410,414,398],"group_six":[0,0,0],"total_val":[13,5,10,9,6],"bs_form":["100","000","001"],"oe_form":["010","100","000"],"pc_form":["000","000","000"],"other_form":["211","110","100"],"span":[7,4,6,7,6],"mantissa":[3,5,0,9,6],"miss_data":[[28,5,18,2,17,12,3,13,8,31],[7,1,16,12,24,17,1,4,8,3],[10,5,55,4,4,9,43,1,2,17],["0",10,15,2,14,9,16,8,3,4],[5,1,8,13,4,11,6,3,14,6]]},{"issue":"201810200710","lottery":["5","9","4","4","6"],"pair":[502,492],"leopard":[547,544,547],"group_three":[411,0,0],"group_six":[0,144,157],"total_val":[18,17,14,14,10],"bs_form":["110","100","001"],"oe_form":["110","100","000"],"pc_form":["100","000","000"],"other_form":["201","011","110"],"span":[5,5,2,4,2],"mantissa":[8,7,4,4,0],"miss_data":[[29,6,19,3,18,5,4,14,1,32],[8,1,17,13,25,18,2,5,9,9],[11,6,56,5,4,10,44,2,3,18],[1,11,16,3,4,10,17,9,4,5],[6,2,9,14,5,12,6,4,15,7]]},{"issue":"201810200709","lottery":["0","0","9","1","9"],"pair":[0,493],"leopard":[548,545,548],"group_three":[0,415,0],"group_six":[145,0,158],"total_val":[9,10,19,0,10],"bs_form":["001","010","101"],"oe_form":["001","011","111"],"pc_form":["000","000","000"],"other_form":["000","001","010"],"span":[9,9,8,0,8],"mantissa":[9,0,9,0,0],"miss_data":[["0",7,20,4,19,1,5,15,2,33],["0",2,18,14,26,19,3,6,10,1],[12,7,57,6,1,11,45,3,4,9],[2,1,17,4,1,11,18,10,5,6],[7,3,10,15,6,13,1,5,16,9]]},{"issue":"201810200708","lottery":["4","8","4","2","1"],"pair":[503,494],"leopard":[549,546,549],"group_three":[0,416,399],"group_six":[146,0,0],"total_val":[16,14,7,12,3],"bs_form":["010","100","000"],"oe_form":["000","000","001"],"pc_form":["000","001","010"],"other_form":["121","212","121"],"span":[4,6,3,4,1],"mantissa":[6,4,7,2,3],"miss_data":[[1,8,21,5,4,2,6,16,3,34],[1,3,19,15,27,20,4,7,8,2],[13,8,58,7,4,12,46,4,5,1],[3,1,2,5,2,12,19,11,6,7],[8,1,11,16,7,14,2,6,17,1]]},{"issue":"201810200707","lottery":["3","3","1","7","1"],"pair":[0,495],"leopard":[550,547,550],"group_three":[0,417,0],"group_six":[147,0,159],"total_val":[7,11,9,6,8],"bs_form":["000","001","010"],"oe_form":["111","111","111"],"pc_form":["110","101","010"],"other_form":["001","011","111"],"span":[2,6,6,0,6],"mantissa":[7,1,9,6,8],"miss_data":[[2,9,22,3,1,3,7,17,4,35],[2,4,20,3,28,21,5,8,1,3],[14,1,59,8,1,13,47,5,6,2],[4,2,1,6,3,13,20,7,7,8],[9,1,12,17,8,15,3,7,18,2]]},{"issue":"201810200706","lottery":["8","2","8","0","8"],"pair":[504,496],"leopard":[551,548,551],"group_three":[0,418,0],"group_six":[148,0,160],"total_val":[18,10,16,10,8],"bs_form":["101","010","101"],"oe_form":["000","000","000"],"pc_form":["010","100","000"],"other_form":["222","220","202"],"span":[6,8,8,6,8],"mantissa":[8,0,6,0,8],"miss_data":[[3,10,23,1,2,4,8,18,8,36],[3,5,2,1,29,22,6,9,2,4],[15,1,60,9,2,14,48,6,8,3],["0",3,2,7,4,14,21,1,8,9],[10,1,13,18,9,16,4,8,8,3]]},{"issue":"201810200705","lottery":["7","8","1","5","5"],"pair":[505,0],"leopard":[552,549,552],"group_three":[412,419,0],"group_six":[0,0,161],"total_val":[16,14,11,15,10],"bs_form":["110","101","011"],"oe_form":["101","011","111"],"pc_form":["100","001","011"],"other_form":["121","212","122"],"span":[7,7,4,1,0],"mantissa":[6,4,1,5,0],"miss_data":[[4,11,24,2,3,5,9,7,1,37],[4,6,1,2,30,23,7,10,8,5],[16,1,61,10,3,15,49,7,1,4],[1,4,3,8,5,5,22,2,9,10],[11,2,14,19,10,5,5,9,1,4]]},{"issue":"201810200704","lottery":["2","3","0","1","7"],"pair":[506,497],"leopard":[553,550,553],"group_three":[413,420,400],"group_six":[0,0,0],"total_val":[5,4,8,5,8],"bs_form":["000","000","001"],"oe_form":["010","101","011"],"pc_form":["110","100","001"],"other_form":["200","001","011"],"span":[3,3,7,1,6],"mantissa":[5,4,8,5,8],"miss_data":[[5,12,2,3,4,6,10,1,2,38],[5,7,2,3,31,24,8,11,1,6],["0",1,62,11,4,16,50,8,2,5],[2,1,4,9,6,1,23,3,10,11],[12,3,15,20,11,1,6,7,2,5]]},{"issue":"201810200703","lottery":["7","1","6","4","7"],"pair":[507,498],"leopard":[554,551,554],"group_three":[414,421,401],"group_six":[0,0,0],"total_val":[14,11,17,8,11],"bs_form":["101","010","101"],"oe_form":["110","100","001"],"pc_form":["100","000","001"],"other_form":["110","101","011"],"span":[6,5,3,6,3],"mantissa":[4,1,7,8,1],"miss_data":[[6,13,1,4,5,7,11,7,3,39],[6,1,3,1,32,25,9,12,2,7],[1,2,63,12,5,17,6,9,3,6],[3,1,5,10,4,2,24,4,11,12],[13,4,16,21,12,2,7,7,3,6]]},{"issue":"201810200702","lottery":["3","9","6","3","0"],"pair":[508,499],"leopard":[555,552,555],"group_three":[415,422,402],"group_six":[0,0,0],"total_val":[18,18,9,12,3],"bs_form":["011","110","100"],"oe_form":["110","101","010"],"pc_form":["100","001","010"],"other_form":["000","000","000"],"span":[6,6,6,6,3],"mantissa":[8,8,9,2,3],"miss_data":[[7,14,2,3,6,8,12,1,4,40],[7,1,4,2,33,26,10,13,3,9],[2,3,64,13,6,18,6,10,4,7],[4,2,6,3,1,3,25,5,12,13],["0",5,17,22,13,3,8,1,4,7]]},{"issue":"201810200701","lottery":["2","9","9","5","4"],"pair":[509,500],"leopard":[556,553,556],"group_three":[0,0,403],"group_six":[149,145,0],"total_val":[20,23,18,11,9],"bs_form":["011","111","110"],"oe_form":["011","111","110"],"pc_form":["100","001","010"],"other_form":["200","002","021"],"span":[7,4,5,7,1],"mantissa":[0,3,8,1,9],"miss_data":[[8,15,2,1,7,9,13,2,5,41],[8,2,5,3,34,27,11,14,4,9],[3,4,65,14,7,19,1,11,5,9],[5,3,7,1,2,5,26,6,13,14],[1,6,18,23,4,4,9,2,5,8]]},{"issue":"201810200700","lottery":["9","3","9","5","1"],"pair":[510,501],"leopard":[557,554,557],"group_three":[0,423,404],"group_six":[150,0,0],"total_val":[21,17,15,12,6],"bs_form":["101","011","110"],"oe_form":["111","111","111"],"pc_form":["010","101","010"],"other_form":["000","002","021"],"span":[6,6,8,6,4],"mantissa":[1,7,5,2,6],"miss_data":[[9,16,1,2,8,10,14,3,6,9],[9,3,6,3,35,28,12,15,5,1],[4,5,66,15,8,20,2,12,6,9],[6,4,8,2,3,5,27,7,14,15],[2,1,19,24,1,5,10,3,6,9]]},{"issue":"201810200699","lottery":["5","3","5","9","5"],"pair":[511,502],"leopard":[558,555,558],"group_three":[0,424,0],"group_six":[151,0,162],"total_val":[13,17,19,8,14],"bs_form":["101","011","111"],"oe_form":["111","111","111"],"pc_form":["111","110","101"],"other_form":["202","020","202"],"span":[2,6,4,2,4],"mantissa":[3,7,9,8,4],"miss_data":[[10,17,2,3,9,5,15,4,7,1],[10,4,7,3,36,29,13,16,6,2],[5,6,67,16,9,5,3,13,7,1],[7,5,9,3,4,1,28,8,15,9],[3,1,20,25,2,5,11,4,7,10]]},{"issue":"201810200698","lottery":["7","0","0","9","6"],"pair":[512,503],"leopard":[559,556,559],"group_three":[0,0,405],"group_six":[152,146,0],"total_val":[7,9,15,7,15],"bs_form":["100","001","011"],"oe_form":["100","001","010"],"pc_form":["100","000","000"],"other_form":["100","000","000"],"span":[7,9,9,7,3],"mantissa":[7,9,5,7,5],"miss_data":[[11,18,3,4,10,1,16,7,8,2],["0",5,8,1,37,30,14,17,7,3],["0",7,68,17,10,1,4,14,8,2],[8,6,10,4,5,2,29,9,16,9],[4,2,21,26,3,1,6,5,8,11]]},{"issue":"201810200697","lottery":["3","9","7","1","4"],"pair":[513,504],"leopard":[560,557,560],"group_three":[416,425,406],"group_six":[0,0,0],"total_val":[19,17,12,12,5],"bs_form":["011","110","100"],"oe_form":["111","111","110"],"pc_form":["101","010","100"],"other_form":["001","011","111"],"span":[6,8,6,6,3],"mantissa":[9,7,2,2,5],"miss_data":[[12,19,4,3,11,2,17,1,9,3],[1,6,9,2,38,31,15,18,8,9],[1,8,69,18,11,2,5,7,9,3],[9,1,11,5,6,3,30,10,17,1],[5,3,22,27,4,2,1,6,9,12]]},{"issue":"201810200696","lottery":["9","4","7","5","6"],"pair":[514,505],"leopard":[561,558,561],"group_three":[417,426,407],"group_six":[0,0,0],"total_val":[20,16,18,13,11],"bs_form":["101","011","111"],"oe_form":["101","011","110"],"pc_form":["001","011","110"],"other_form":["011","112","120"],"span":[5,3,2,5,1],"mantissa":[0,6,8,3,1],"miss_data":[[13,20,5,1,12,3,18,2,10,9],[2,7,10,3,4,32,16,19,9,1],[2,9,70,19,12,3,6,7,10,4],[10,1,12,6,7,5,31,11,18,2],[6,4,23,28,1,3,6,7,10,13]]},{"issue":"201810200695","lottery":["9","7","2","8","7"],"pair":[515,506],"leopard":[562,559,562],"group_three":[418,427,408],"group_six":[0,0,0],"total_val":[18,17,17,16,15],"bs_form":["110","101","011"],"oe_form":["110","100","001"],"pc_form":["011","110","101"],"other_form":["012","122","221"],"span":[7,6,6,2,1],"mantissa":[8,7,7,6,5],"miss_data":[[14,21,6,2,13,4,19,3,11,9],[3,8,11,4,1,33,17,7,10,2],[3,10,2,20,13,4,7,1,11,5],[11,2,13,7,8,1,32,12,8,3],[7,5,24,29,2,4,1,7,11,14]]},{"issue":"201810200694","lottery":["1","8","0","7","6"],"pair":[516,507],"leopard":[563,560,563],"group_three":[419,428,409],"group_six":[0,0,0],"total_val":[9,15,13,9,13],"bs_form":["010","101","011"],"oe_form":["100","001","010"],"pc_form":["000","001","010"],"other_form":["120","201","010"],"span":[8,8,7,7,1],"mantissa":[9,5,3,9,3],"miss_data":[[15,1,7,3,14,5,20,4,12,1],[4,9,12,5,2,34,18,1,8,3],["0",11,1,21,14,5,8,2,12,6],[12,3,14,8,9,2,33,7,1,4],[8,6,25,30,3,5,6,1,12,15]]},{"issue":"201810200693","lottery":["9","2","4","3","0"],"pair":[517,508],"leopard":[564,561,564],"group_three":[420,429,410],"group_six":[0,0,0],"total_val":[15,9,7,11,3],"bs_form":["100","000","000"],"oe_form":["100","001","010"],"pc_form":["010","101","010"],"other_form":["021","210","100"],"span":[7,2,4,7,3],"mantissa":[5,9,7,1,3],"miss_data":[[16,1,8,4,15,6,21,5,13,9],[5,10,2,6,3,35,19,2,1,4],[1,12,2,22,4,6,9,3,13,7],[13,4,15,3,10,3,34,1,2,5],["0",7,26,31,4,6,1,2,13,16]]},{"issue":"201810200692","lottery":["9","8","1","1","5"],"pair":[518,509],"leopard":[565,562,565],"group_three":[421,0,0],"group_six":[0,147,163],"total_val":[18,10,7,17,6],"bs_form":["110","100","001"],"oe_form":["101","011","111"],"pc_form":["000","000","001"],"other_form":["021","211","112"],"span":[8,7,4,1,4],"mantissa":[8,0,7,7,6],"miss_data":[[17,2,9,5,16,7,22,6,14,9],[6,11,1,7,4,36,20,3,8,5],[2,1,3,23,1,7,10,4,14,8],[14,1,16,1,11,4,35,2,3,6],[1,8,27,32,5,5,2,3,14,17]]},{"issue":"201810200691","lottery":["8","8","9","4","7"],"pair":[0,510],"leopard":[566,563,566],"group_three":[0,430,411],"group_six":[153,0,0],"total_val":[25,21,20,16,11],"bs_form":["111","110","101"],"oe_form":["001","010","101"],"pc_form":["000","000","001"],"other_form":["220","201","011"],"span":[1,5,5,0,3],"mantissa":[5,1,0,6,1],"miss_data":[[18,3,10,6,17,8,23,7,8,1],[7,12,2,8,5,37,21,4,8,6],[3,1,4,24,2,8,11,5,15,9],[15,1,17,2,4,5,36,3,4,7],[2,9,28,33,6,1,3,7,15,18]]},{"issue":"201810200690","lottery":["3","0","1","0","0"],"pair":[519,0],"leopard":[567,564,567],"group_three":[422,0,0],"group_six":[0,148,164],"total_val":[4,1,1,3,0],"bs_form":["000","000","000"],"oe_form":["101","010","100"],"pc_form":["100","000","000"],"other_form":["001","010","100"],"span":[3,1,1,3,0],"mantissa":[4,1,1,3,0],"miss_data":[[19,4,11,3,18,9,24,8,1,2],["0",13,3,9,6,38,22,5,1,7],[4,1,5,25,3,9,12,6,16,1],["0",2,18,3,1,6,37,4,5,8],["0",10,29,34,7,2,4,1,16,19]]},{"issue":"201810200689","lottery":["4","4","8","3","9"],"pair":[0,511],"leopard":[568,565,568],"group_three":[0,431,412],"group_six":[154,0,0],"total_val":[16,15,20,8,12],"bs_form":["001","010","101"],"oe_form":["000","001","011"],"pc_form":["000","001","010"],"other_form":["112","120","200"],"span":[4,5,6,0,6],"mantissa":[6,5,0,8,2],"miss_data":[[20,5,12,1,4,10,25,9,2,3],[1,14,4,10,4,39,23,6,2,8],[5,1,6,26,4,10,13,7,8,2],[1,3,19,3,2,7,38,5,6,9],[1,11,30,35,8,3,5,2,17,9]]},{"issue":"201810200688","lottery":["6","9","5","7","0"],"pair":[520,512],"leopard":[569,566,569],"group_three":[423,432,413],"group_six":[0,0,0],"total_val":[20,21,12,15,7],"bs_form":["111","111","110"],"oe_form":["011","111","110"],"pc_form":["001","011","110"],"other_form":["002","021","210"],"span":[4,4,7,3,7],"mantissa":[0,1,2,5,7],"miss_data":[[21,6,13,2,1,11,6,10,3,4],[2,15,5,11,1,40,24,7,3,9],[6,2,7,27,5,5,14,8,1,3],[2,4,20,1,3,8,39,7,7,10],["0",12,31,36,9,4,6,3,18,1]]},{"issue":"201810200687","lottery":["7","0","3","5","4"],"pair":[521,513],"leopard":[570,567,570],"group_three":[424,433,414],"group_six":[0,0,0],"total_val":[10,8,12,7,9],"bs_form":["100","001","010"],"oe_form":["101","011","110"],"pc_form":["101","011","110"],"other_form":["100","002","021"],"span":[7,5,2,7,1],"mantissa":[0,8,2,7,9],"miss_data":[[22,7,14,3,2,12,1,7,4,5],["0",16,6,12,2,41,25,8,4,1],[7,3,8,3,6,1,15,9,2,4],[3,5,21,2,4,5,40,1,8,11],[1,13,32,37,4,5,7,4,19,2]]},{"issue":"201810200686","lottery":["3","5","5","6","2"],"pair":[522,514],"leopard":[571,568,571],"group_three":[0,0,415],"group_six":[155,149,0],"total_val":[13,16,13,8,8],"bs_form":["011","111","110"],"oe_form":["111","110","100"],"pc_form":["111","110","101"],"other_form":["022","220","202"],"span":[2,1,4,2,4],"mantissa":[3,6,3,8,8],"miss_data":[[23,8,15,3,3,13,2,1,5,6],[1,17,7,13,3,5,26,9,5,2],[8,4,9,1,7,5,16,10,3,5],[4,6,22,3,5,1,6,2,9,12],[2,14,2,38,1,6,8,5,20,3]]},{"issue":"201810200685","lottery":["9","7","0","3","1"],"pair":[523,515],"leopard":[572,569,572],"group_three":[425,434,416],"group_six":[0,0,0],"total_val":[16,10,4,16,4],"bs_form":["110","100","000"],"oe_form":["110","101","011"],"pc_form":["010","101","010"],"other_form":["010","100","001"],"span":[9,7,3,2,2],"mantissa":[6,0,4,6,4],"miss_data":[[24,9,16,1,4,14,3,2,6,9],[2,18,8,14,4,1,27,7,6,3],["0",5,10,2,8,1,17,11,4,6],[5,7,23,3,6,2,1,3,10,13],[3,1,1,39,2,7,9,6,21,4]]},{"issue":"201810200684","lottery":["4","9","7","2","4"],"pair":[524,516],"leopard":[573,570,573],"group_three":[426,435,417],"group_six":[0,0,0],"total_val":[20,18,13,13,6],"bs_form":["011","110","100"],"oe_form":["011","110","100"],"pc_form":["001","011","110"],"other_form":["101","012","121"],"span":[5,7,5,5,2],"mantissa":[0,8,3,3,6],"miss_data":[[25,10,17,2,4,15,4,3,7,1],[3,19,9,15,5,2,28,1,7,9],[1,6,11,3,9,2,18,7,5,7],[6,8,2,1,7,3,2,4,11,14],[4,1,2,40,4,8,10,7,22,5]]},{"issue":"201810200683","lottery":["9","7","6","8","5"],"pair":[525,517],"leopard":[574,571,574],"group_three":[427,436,418],"group_six":[0,0,0],"total_val":[22,21,19,16,13],"bs_form":["111","111","111"],"oe_form":["110","100","001"],"pc_form":["010","100","001"],"other_form":["010","102","022"],"span":[3,2,3,2,3],"mantissa":[2,1,9,6,3],"miss_data":[[26,11,18,3,1,16,5,4,8,9],[4,20,10,16,6,3,29,7,8,1],[2,7,12,4,10,3,6,1,6,8],[7,9,1,2,8,4,3,5,8,15],[5,2,3,41,1,5,11,8,23,6]]},{"issue":"201810200682","lottery":["7","9","2","1","7"],"pair":[526,518],"leopard":[575,572,575],"group_three":[428,437,419],"group_six":[0,0,0],"total_val":[18,12,10,16,8],"bs_form":["110","100","001"],"oe_form":["110","101","011"],"pc_form":["101","010","101"],"other_form":["102","021","211"],"span":[7,8,6,2,6],"mantissa":[8,2,0,6,8],"miss_data":[[27,12,19,4,2,17,6,7,9,1],[5,21,11,17,7,4,30,1,9,9],[3,8,2,5,11,4,1,2,7,9],[8,1,2,3,9,5,4,6,1,16],[6,3,4,42,2,1,12,7,24,7]]},{"issue":"201810200681","lottery":["6","8","7","5","4"],"pair":[527,519],"leopard":[576,573,576],"group_three":[429,438,420],"group_six":[0,0,0],"total_val":[21,20,16,14,9],"bs_form":["111","111","110"],"oe_form":["001","011","110"],"pc_form":["001","011","110"],"other_form":["021","212","121"],"span":[2,3,3,2,1],"mantissa":[1,0,6,4,9],"miss_data":[[28,13,20,5,3,18,6,1,10,2],[6,22,12,18,8,5,31,2,8,1],[4,9,1,6,12,5,2,7,8,10],[9,1,3,4,10,5,5,7,2,17],[7,4,5,43,4,2,13,1,25,8]]},{"issue":"201810200680","lottery":["4","2","8","2","7"],"pair":[528,520],"leopard":[577,574,577],"group_three":[430,0,421],"group_six":[0,150,0],"total_val":[14,12,17,6,9],"bs_form":["001","010","101"],"oe_form":["000","000","001"],"pc_form":["010","101","011"],"other_form":["122","222","221"],"span":[6,6,6,2,5],"mantissa":[4,2,7,6,9],"miss_data":[[29,14,21,6,4,19,1,2,11,3],[7,23,2,19,9,6,32,3,1,2],[5,10,2,7,13,6,3,1,8,11],[10,2,2,5,11,1,6,8,3,18],[8,5,6,44,1,3,14,7,26,9]]},{"issue":"201810200679","lottery":["8","3","7","9","7"],"pair":[529,521],"leopard":[578,575,578],"group_three":[431,439,0],"group_six":[0,0,165],"total_val":[18,19,23,11,16],"bs_form":["101","011","111"],"oe_form":["011","111","111"],"pc_form":["011","110","101"],"other_form":["201","010","101"],"span":[5,6,2,5,2],"mantissa":[8,9,3,1,6],"miss_data":[[30,15,22,7,1,20,2,3,8,4],[8,24,1,3,10,7,33,4,2,3],[6,11,3,8,14,7,4,7,1,12],[11,3,1,6,12,2,7,9,4,9],[9,6,7,45,2,4,15,7,27,10]]},{"issue":"201810200678","lottery":["0","5","5","2","8"],"pair":[530,522],"leopard":[579,576,579],"group_three":[0,0,422],"group_six":[156,151,0],"total_val":[10,12,15,5,10],"bs_form":["011","110","101"],"oe_form":["011","110","100"],"pc_form":["011","111","110"],"other_form":["022","222","222"],"span":[5,3,6,5,6],"mantissa":[0,2,5,5,0],"miss_data":[["0",16,23,8,2,21,3,4,1,5],[9,25,2,1,11,5,34,5,3,4],[7,12,4,9,15,5,5,1,2,13],[12,4,2,7,13,3,8,10,5,1],[10,7,8,46,3,5,16,1,8,11]]},{"issue":"201810200677","lottery":["1","4","2","0","6"],"pair":[531,523],"leopard":[580,577,580],"group_three":[432,440,423],"group_six":[0,0,0],"total_val":[7,6,8,5,6],"bs_form":["000","000","001"],"oe_form":["100","000","000"],"pc_form":["001","010","100"],"other_form":["112","120","200"],"span":[3,4,6,3,6],"mantissa":[7,6,8,5,6],"miss_data":[[1,1,24,9,3,22,4,5,2,6],[10,26,3,2,4,1,35,6,4,5],[8,13,2,10,16,1,6,2,3,14],["0",5,1,8,14,4,9,11,6,2],[11,8,9,47,4,6,6,2,1,12]]},{"issue":"201810200676","lottery":["3","6","4","1","4"],"pair":[532,524],"leopard":[581,578,581],"group_three":[433,441,0],"group_six":[0,0,166],"total_val":[13,11,9,9,5],"bs_form":["010","100","000"],"oe_form":["100","001","010"],"pc_form":["100","000","000"],"other_form":["001","011","111"],"span":[3,5,3,3,3],"mantissa":[3,1,9,9,5],"miss_data":[[2,1,25,3,4,23,5,6,3,7],[11,27,4,3,1,2,6,7,5,6],[9,14,1,11,4,2,7,3,4,15],[1,1,2,9,15,5,10,12,7,3],[12,9,10,48,4,7,1,3,2,13]]},{"issue":"201810200675","lottery":["1","5","7","2","3"],"pair":[533,525],"leopard":[582,579,582],"group_three":[434,442,424],"group_six":[0,0,0],"total_val":[13,14,12,6,5],"bs_form":["011","110","100"],"oe_form":["111","110","101"],"pc_form":["011","111","111"],"other_form":["121","212","120"],"span":[6,5,5,4,1],"mantissa":[3,4,2,6,5],"miss_data":[[3,1,26,1,5,24,6,7,4,8],[12,28,5,4,2,5,1,8,6,7],[10,15,2,12,1,3,8,7,5,16],[2,1,2,10,16,6,11,13,8,4],[13,10,11,3,1,8,2,4,3,14]]},{"issue":"201810200674","lottery":["0","3","2","3","0"],"pair":[534,526],"leopard":[583,580,583],"group_three":[435,0,425],"group_six":[0,152,0],"total_val":[5,8,5,3,3],"bs_form":["000","000","000"],"oe_form":["010","101","010"],"pc_form":["011","111","110"],"other_form":["002","020","200"],"span":[3,1,3,3,3],"mantissa":[5,8,5,3,3],"miss_data":[["0",1,27,2,6,25,7,8,5,9],[13,29,6,3,3,1,2,9,7,8],[11,16,2,13,2,4,9,1,6,17],[3,2,1,3,17,7,12,14,9,5],["0",11,12,1,2,9,3,5,4,15]]},{"issue":"201810200673","lottery":["8","3","0","4","5"],"pair":[535,527],"leopard":[584,581,584],"group_three":[436,443,426],"group_six":[0,0,0],"total_val":[11,7,9,11,9],"bs_form":["100","000","001"],"oe_form":["010","100","001"],"pc_form":["010","100","001"],"other_form":["200","001","012"],"span":[8,4,5,5,1],"mantissa":[1,7,9,1,9],"miss_data":[[1,2,28,3,7,26,8,9,8,10],[14,30,7,3,4,2,3,10,8,9],["0",17,1,14,3,5,10,2,7,18],[4,3,2,1,4,8,13,15,10,6],[1,12,13,2,3,5,4,6,5,16]]},{"issue":"201810200672","lottery":["8","4","7","2","4"],"pair":[536,528],"leopard":[585,582,585],"group_three":[437,444,427],"group_six":[0,0,0],"total_val":[19,13,13,12,6],"bs_form":["101","010","100"],"oe_form":["001","010","100"],"pc_form":["001","011","110"],"other_form":["211","112","121"],"span":[4,5,5,4,2],"mantissa":[9,3,3,2,6],"miss_data":[[2,3,29,4,8,27,9,10,8,11],[15,31,8,1,4,3,4,11,9,10],[1,18,2,15,4,6,11,7,8,19],[5,4,2,2,1,9,14,16,11,7],[2,13,14,3,4,1,5,7,6,17]]},{"issue":"201810200671","lottery":["5","9","7","2","5"],"pair":[537,529],"leopard":[586,583,586],"group_three":[438,445,428],"group_six":[0,0,0],"total_val":[21,18,14,14,7],"bs_form":["111","110","101"],"oe_form":["111","110","101"],"pc_form":["101","011","111"],"other_form":["201","012","122"],"span":[4,7,5,4,3],"mantissa":[1,8,4,4,7],"miss_data":[[3,4,30,5,9,5,10,11,1,12],[16,32,9,2,1,4,5,12,10,9],[2,19,3,16,5,7,12,7,9,20],[6,5,2,3,2,10,15,17,12,8],[3,14,15,4,1,5,6,8,7,18]]},{"issue":"201810200670","lottery":["1","2","5","1","7"],"pair":[538,530],"leopard":[587,584,587],"group_three":[439,446,429],"group_six":[0,0,0],"total_val":[8,8,13,3,8],"bs_form":["001","010","101"],"oe_form":["101","011","111"],"pc_form":["011","110","101"],"other_form":["122","221","211"],"span":[4,4,6,1,6],"mantissa":[8,8,3,3,8],"miss_data":[[4,1,31,6,10,1,11,12,2,13],[17,33,2,3,2,5,6,13,11,1],[3,20,4,17,6,5,13,1,10,21],[7,1,1,4,3,11,16,18,13,9],[4,15,16,5,2,1,7,7,8,19]]},{"issue":"201810200669","lottery":["8","3","0","7","2"],"pair":[539,531],"leopard":[588,585,588],"group_three":[440,447,430],"group_six":[0,0,0],"total_val":[11,10,9,11,9],"bs_form":["100","001","010"],"oe_form":["010","101","010"],"pc_form":["010","101","011"],"other_form":["200","001","012"],"span":[8,7,7,5,5],"mantissa":[1,0,9,1,9],"miss_data":[[5,1,32,7,11,2,12,13,8,14],[18,34,1,3,3,6,7,14,12,2],["0",21,5,18,7,1,14,2,11,22],[8,1,2,5,4,12,17,7,14,10],[5,16,2,6,3,2,8,1,9,20]]},{"issue":"201810200668","lottery":["5","2","4","7","5"],"pair":[540,532],"leopard":[589,586,589],"group_three":[441,448,431],"group_six":[0,0,0],"total_val":[11,13,16,7,12],"bs_form":["100","001","011"],"oe_form":["100","001","011"],"pc_form":["110","101","011"],"other_form":["221","211","112"],"span":[3,5,3,3,2],"mantissa":[1,3,6,7,2],"miss_data":[[6,2,33,8,12,5,13,14,1,15],[19,35,2,1,4,7,8,15,13,3],[1,22,6,19,4,2,15,3,12,23],[9,2,3,6,5,13,18,7,15,11],[6,17,1,7,4,5,9,2,10,21]]},{"issue":"201810200667","lottery":["3","5","2","4","0"],"pair":[541,533],"leopard":[590,587,590],"group_three":[442,449,432],"group_six":[0,0,0],"total_val":[10,11,6,8,4],"bs_form":["010","100","000"],"oe_form":["110","100","000"],"pc_form":["111","110","100"],"other_form":["022","221","210"],"span":[3,3,4,2,4],"mantissa":[0,1,6,8,4],"miss_data":[[7,3,34,3,13,1,14,15,2,16],[20,36,1,2,5,5,9,16,14,4],[2,23,2,20,1,3,16,4,13,24],[10,3,4,7,4,14,19,1,16,12],["0",18,2,8,5,1,10,3,11,22]]},{"issue":"201810200666","lottery":["1","0","5","1","2"],"pair":[542,534],"leopard":[591,588,591],"group_three":[443,450,433],"group_six":[0,0,0],"total_val":[6,6,8,1,3],"bs_form":["001","010","100"],"oe_form":["101","011","110"],"pc_form":["001","010","101"],"other_form":["102","021","212"],"span":[5,5,4,1,1],"mantissa":[6,6,8,1,3],"miss_data":[[8,1,35,1,14,2,15,16,3,17],["0",37,2,3,6,1,10,17,15,5],[3,24,1,21,2,5,17,5,14,25],[11,1,5,8,1,15,20,2,17,13],[1,19,2,9,6,2,11,4,12,23]]},{"issue":"201810200665","lottery":["5","0","1","0","0"],"pair":[543,0],"leopard":[592,589,592],"group_three":[444,0,0],"group_six":[0,153,167],"total_val":[6,1,1,5,0],"bs_form":["100","000","000"],"oe_form":["101","010","100"],"pc_form":["100","000","000"],"other_form":["201","010","100"],"span":[5,1,1,5,0],"mantissa":[6,1,1,5,0],"miss_data":[[9,1,36,2,15,5,16,17,4,18],["0",38,3,4,7,2,11,18,16,6],[4,1,2,22,3,1,18,6,15,26],["0",1,6,9,2,16,21,3,18,14],["0",20,1,10,7,3,12,5,13,24]]},{"issue":"201810200664","lottery":["7","0","3","7","0"],"pair":[544,535],"leopard":[593,590,593],"group_three":[445,451,434],"group_six":[0,0,0],"total_val":[10,10,10,7,7],"bs_form":["100","001","010"],"oe_form":["101","011","110"],"pc_form":["101","011","110"],"other_form":["100","001","010"],"span":[7,7,7,7,7],"mantissa":[0,0,0,7,7],"miss_data":[[10,2,37,3,16,1,17,7,5,19],["0",39,4,5,8,3,12,19,17,7],[5,1,3,3,4,2,19,7,16,27],[1,2,7,10,3,17,22,7,19,15],["0",21,2,11,8,4,13,6,14,25]]},{"issue":"201810200663","lottery":["7","3","8","1","6"],"pair":[545,536],"leopard":[594,591,594],"group_three":[446,452,435],"group_six":[0,0,0],"total_val":[18,12,15,10,7],"bs_form":["101","010","101"],"oe_form":["110","101","010"],"pc_form":["110","100","000"],"other_form":["102","021","210"],"span":[5,7,7,4,5],"mantissa":[8,2,5,0,7],"miss_data":[[11,3,38,4,17,2,18,7,6,20],[1,40,5,3,9,4,13,20,18,8],[6,2,4,1,5,3,20,8,8,28],[2,1,8,11,4,18,23,1,20,16],[1,22,3,12,9,5,6,7,15,26]]},{"issue":"201810200662","lottery":["4","7","5","8","9"],"pair":[546,537],"leopard":[595,592,595],"group_three":[447,453,436],"group_six":[0,0,0],"total_val":[16,20,22,11,17],"bs_form":["011","111","111"],"oe_form":["011","110","101"],"pc_form":["011","110","100"],"other_form":["112","122","220"],"span":[3,3,4,3,1],"mantissa":[6,0,2,1,7],"miss_data":[[12,4,39,5,4,3,19,1,7,21],[2,41,6,1,10,5,14,7,19,9],[7,3,5,2,6,5,21,9,1,29],[3,1,9,12,5,19,24,2,8,17],[2,23,4,13,10,6,1,8,16,9]]},{"issue":"201810200661","lottery":["8","3","9","1","1"],"pair":[547,0],"leopard":[596,593,596],"group_three":[448,454,0],"group_six":[0,0,168],"total_val":[20,13,11,11,2],"bs_form":["101","010","100"],"oe_form":["011","111","111"],"pc_form":["010","100","000"],"other_form":["200","001","011"],"span":[6,8,8,5,0],"mantissa":[0,3,1,1,2],"miss_data":[[13,5,40,6,1,4,20,2,8,22],[3,42,7,3,11,6,15,1,20,10],[8,4,6,3,7,1,22,10,2,9],[4,1,10,13,6,20,25,3,1,18],[3,1,5,14,11,7,2,9,17,1]]},{"issue":"201810200660","lottery":["5","9","3","8","7"],"pair":[548,538],"leopard":[597,594,597],"group_three":[449,455,437],"group_six":[0,0,0],"total_val":[17,20,18,14,15],"bs_form":["110","101","011"],"oe_form":["111","110","101"],"pc_form":["101","010","101"],"other_form":["200","002","021"],"span":[6,6,5,4,1],"mantissa":[7,0,8,4,5],"miss_data":[[14,6,41,7,2,5,21,3,1,23],[4,43,8,1,12,7,16,2,21,9],[9,5,7,3,8,2,23,11,3,1],[5,1,11,14,7,21,26,4,8,19],[4,1,6,15,12,8,3,7,18,2]]},{"issue":"201810200659","lottery":["3","6","0","6","4"],"pair":[549,539],"leopard":[598,595,598],"group_three":[450,0,438],"group_six":[0,154,0],"total_val":[9,12,10,9,10],"bs_form":["010","101","010"],"oe_form":["100","000","000"],"pc_form":["100","000","000"],"other_form":["000","000","001"],"span":[6,6,6,3,2],"mantissa":[9,2,0,9,0],"miss_data":[[15,7,42,3,3,1,22,4,2,24],[5,44,9,2,13,8,6,3,22,1],["0",6,8,1,9,3,24,12,4,2],[6,2,12,15,8,22,6,5,1,20],[5,2,7,16,4,9,4,1,19,3]]},{"issue":"201810200658","lottery":["9","9","9","6","0"],"pair":[0,540],"leopard":[0,596,599],"group_three":[451,0,439],"group_six":[157,155,0],"total_val":[27,24,15,18,6],"bs_form":["111","111","110"],"oe_form":["111","110","100"],"pc_form":["000","000","000"],"other_form":["000","000","000"],"span":[0,3,9,0,6],"mantissa":[7,4,5,8,6],"miss_data":[[16,8,43,1,4,2,23,5,3,9],[6,45,10,3,14,9,1,4,23,9],[1,7,9,2,10,4,25,13,5,9],[7,3,13,16,9,23,6,6,2,21],["0",3,8,17,1,10,5,2,20,4]]},{"issue":"201810200657","lottery":["6","5","1","3","1"],"pair":[550,541],"leopard":[599,597,600],"group_three":[452,456,0],"group_six":[0,0,169],"total_val":[12,9,5,11,4],"bs_form":["110","100","000"],"oe_form":["011","111","111"],"pc_form":["010","101","010"],"other_form":["021","210","101"],"span":[5,4,2,1,2],"mantissa":[2,9,5,1,4],"miss_data":[[17,9,44,2,5,3,6,6,4,1],[7,46,11,4,15,5,2,5,24,1],[2,1,10,3,11,5,26,14,6,1],[8,4,14,3,10,24,1,7,3,22],[1,1,9,18,2,11,6,3,21,5]]},{"issue":"201810200656","lottery":["0","2","0","3","5"],"pair":[551,542],"leopard":[600,598,601],"group_three":[0,457,440],"group_six":[158,0,0],"total_val":[2,5,8,2,8],"bs_form":["000","000","001"],"oe_form":["000","001","011"],"pc_form":["010","101","011"],"other_form":["020","200","002"],"span":[2,3,5,2,2],"mantissa":[2,5,8,2,8],"miss_data":[["0",10,45,3,6,4,1,7,5,2],[8,47,2,5,16,1,3,6,25,2],["0",1,11,4,12,6,27,15,7,2],[9,5,15,3,11,25,2,8,4,23],[2,1,10,19,3,5,7,4,22,6]]},{"issue":"201810200655","lottery":["9","4","2","1","4"],"pair":[552,543],"leopard":[601,599,602],"group_three":[453,458,441],"group_six":[0,0,0],"total_val":[15,7,7,13,5],"bs_form":["100","000","000"],"oe_form":["100","001","010"],"pc_form":["001","010","100"],"other_form":["012","121","211"],"span":[7,3,3,5,3],"mantissa":[5,7,7,3,5],"miss_data":[[1,11,46,4,7,5,2,8,6,9],[9,48,1,6,4,2,4,7,26,3],[1,2,2,5,13,7,28,16,8,3],[10,1,16,1,12,26,3,9,5,24],[3,2,11,20,4,1,8,5,23,7]]},{"issue":"201810200654","lottery":["9","8","1","5","5"],"pair":[553,0],"leopard":[602,600,603],"group_three":[454,459,0],"group_six":[0,0,170],"total_val":[18,14,11,17,10],"bs_form":["110","101","011"],"oe_form":["101","011","111"],"pc_form":["000","001","011"],"other_form":["021","212","122"],"span":[8,7,4,1,0],"mantissa":[8,4,1,7,0],"miss_data":[[2,12,47,5,8,6,3,9,7,9],[10,49,2,7,1,3,5,8,8,4],[2,1,1,6,14,8,29,17,9,4],[11,1,17,2,13,5,4,10,6,25],[4,3,12,21,1,5,9,6,24,8]]},{"issue":"201810200653","lottery":["4","3","7","2","9"],"pair":[554,544],"leopard":[603,601,604],"group_three":[455,460,442],"group_six":[0,0,0],"total_val":[14,12,18,7,11],"bs_form":["001","010","101"],"oe_form":["011","110","101"],"pc_form":["011","111","110"],"other_form":["101","012","120"],"span":[4,5,7,1,7],"mantissa":[4,2,8,7,1],"miss_data":[[3,13,48,6,4,7,4,10,8,1],[11,50,3,3,2,4,6,9,1,5],[3,1,2,7,15,9,30,7,10,5],[12,2,2,3,14,1,5,11,7,26],[5,4,13,22,2,1,10,7,25,9]]},{"issue":"201810200652","lottery":["9","7","3","8","0"],"pair":[555,545],"leopard":[604,602,605],"group_three":[456,461,443],"group_six":[0,0,0],"total_val":[19,18,11,16,8],"bs_form":["110","101","010"],"oe_form":["111","110","100"],"pc_form":["011","110","100"],"other_form":["010","102","020"],"span":[6,5,8,2,8],"mantissa":[9,8,1,6,8],"miss_data":[[4,14,49,7,1,8,5,11,9,9],[12,51,4,1,3,5,7,7,2,6],[4,2,3,3,16,10,31,1,11,6],[13,3,1,4,15,2,6,12,8,27],["0",5,14,23,3,2,11,8,26,1]]},{"issue":"201810200651","lottery":["3","8","0","8","8"],"pair":[556,0],"leopard":[605,603,606],"group_three":[457,0,0],"group_six":[0,156,171],"total_val":[11,16,16,11,16],"bs_form":["010","101","011"],"oe_form":["100","000","000"],"pc_form":["100","000","000"],"other_form":["020","202","022"],"span":[8,8,8,5,0],"mantissa":[1,6,6,1,6],"miss_data":[[5,15,50,3,2,9,6,12,10,1],[13,52,5,2,4,6,8,1,8,7],["0",3,4,1,17,11,32,2,12,7],[14,4,2,5,16,3,7,13,8,28],[1,6,15,24,4,3,12,9,8,2]]},{"issue":"201810200650","lottery":["9","9","1","8","9"],"pair":[0,546],"leopard":[606,604,607],"group_three":[0,462,444],"group_six":[159,0,0],"total_val":[19,18,18,18,17],"bs_form":["110","101","011"],"oe_form":["111","110","101"],"pc_form":["000","000","000"],"other_form":["001","012","120"],"span":[8,8,8,0,1],"mantissa":[9,8,8,8,7],"miss_data":[[6,16,51,1,3,10,7,13,11,9],[14,53,6,3,5,7,9,2,1,9],[1,1,5,2,18,12,33,3,13,8],[15,5,3,6,17,4,8,14,8,29],[2,7,16,25,5,4,13,10,1,9]]},{"issue":"201810200649","lottery":["9","8","6","4","0"],"pair":[557,547],"leopard":[607,605,608],"group_three":[458,463,445],"group_six":[0,0,0],"total_val":[23,18,10,17,4],"bs_form":["111","110","100"],"oe_form":["100","000","000"],"pc_form":["000","000","000"],"other_form":["020","201","010"],"span":[3,4,6,1,4],"mantissa":[3,8,0,7,4],"miss_data":[[7,17,52,2,4,11,8,14,12,9],[15,54,7,4,6,8,10,3,8,1],[2,1,6,3,19,13,6,4,14,9],[16,6,4,7,4,5,9,15,1,30],["0",8,17,26,6,5,14,11,2,1]]},{"issue":"201810200648","lottery":["6","2","4","7","1"],"pair":[558,548],"leopard":[608,606,609],"group_three":[459,464,446],"group_six":[0,0,0],"total_val":[12,13,12,8,8],"bs_form":["100","001","010"],"oe_form":["000","001","011"],"pc_form":["010","101","010"],"other_form":["021","211","111"],"span":[4,5,6,4,6],"mantissa":[2,3,2,8,8],"miss_data":[[8,18,53,3,5,12,6,15,13,1],[16,55,2,5,7,9,11,4,1,2],[3,2,7,4,4,14,1,5,15,10],[17,7,5,8,1,6,10,7,2,31],[1,1,18,27,7,6,15,12,3,2]]},{"issue":"201810200647","lottery":["1","0","0","9","1"],"pair":[559,549],"leopard":[609,607,610],"group_three":[0,0,447],"group_six":[160,157,0],"total_val":[1,9,10,1,10],"bs_form":["000","001","010"],"oe_form":["100","001","011"],"pc_form":["000","000","000"],"other_form":["100","000","001"],"span":[1,9,9,1,8],"mantissa":[1,9,0,1,0],"miss_data":[[9,1,54,4,6,13,1,16,14,2],["0",56,1,6,8,10,12,5,2,3],["0",3,8,5,1,15,2,6,16,11],[18,8,6,9,2,7,11,1,3,9],[2,1,19,28,8,7,16,13,4,3]]},{"issue":"201810200646","lottery":["6","6","9","2","6"],"pair":[0,550],"leopard":[610,608,611],"group_three":[0,465,448],"group_six":[161,0,0],"total_val":[21,17,17,12,8],"bs_form":["111","110","101"],"oe_form":["001","010","100"],"pc_form":["000","001","010"],"other_form":["000","002","020"],"span":[3,7,7,0,4],"mantissa":[1,7,7,2,8],"miss_data":[[10,1,55,5,7,14,6,17,15,3],[1,57,2,7,9,11,6,6,3,4],[1,4,9,6,2,16,3,7,17,9],[19,9,2,10,3,8,12,2,4,1],[3,1,20,29,9,8,6,14,5,4]]},{"issue":"201810200645","lottery":["0","1","2","1","1"],"pair":[560,0],"leopard":[611,609,612],"group_three":[460,0,0],"group_six":[0,158,172],"total_val":[3,4,4,1,2],"bs_form":["000","000","000"],"oe_form":["010","101","011"],"pc_form":["001","010","100"],"other_form":["012","121","211"],"span":[2,1,1,1,0],"mantissa":[3,4,4,1,2],"miss_data":[["0",2,56,6,8,15,1,18,16,4],[2,1,3,8,10,12,1,7,4,5],[2,5,2,7,3,17,4,8,18,1],[20,1,1,11,4,9,13,3,5,2],[4,1,21,30,10,9,1,15,6,5]]},{"issue":"201810200644","lottery":["7","7","1","3","2"],"pair":[0,551],"leopard":[612,610,613],"group_three":[0,466,449],"group_six":[162,0,0],"total_val":[15,11,6,14,5],"bs_form":["110","100","000"],"oe_form":["111","111","110"],"pc_form":["110","101","011"],"other_form":["111","110","102"],"span":[6,6,2,0,1],"mantissa":[5,1,6,4,5],"miss_data":[[1,3,57,7,9,16,2,7,17,5],[3,1,4,9,11,13,2,7,5,6],[3,1,1,8,4,18,5,9,19,2],[21,1,2,3,5,10,14,4,6,3],[5,1,2,31,11,10,2,16,7,6]]},{"issue":"201810200643","lottery":["0","4","7","9","1"],"pair":[561,552],"leopard":[613,611,614],"group_three":[461,467,450],"group_six":[0,0,0],"total_val":[11,20,17,4,10],"bs_form":["001","011","110"],"oe_form":["001","011","111"],"pc_form":["001","010","100"],"other_form":["011","110","101"],"span":[7,5,8,4,8],"mantissa":[1,0,7,4,0],"miss_data":[["0",4,58,8,10,17,3,1,18,6],[4,2,5,10,4,14,3,1,6,7],[4,1,2,9,5,19,6,7,20,3],[22,2,3,1,6,11,15,5,7,9],[6,1,1,32,12,11,3,17,8,7]]},{"issue":"201810200642","lottery":["5","3","3","7","4"],"pair":[562,553],"leopard":[614,612,615],"group_three":[0,0,451],"group_six":[163,159,0],"total_val":[11,13,14,8,11],"bs_form":["100","001","010"],"oe_form":["111","111","110"],"pc_form":["111","111","110"],"other_form":["200","001","011"],"span":[2,4,4,2,3],"mantissa":[1,3,4,8,1],"miss_data":[[1,5,59,9,11,5,4,2,19,7],[5,3,6,3,1,15,4,2,7,8],[5,2,3,3,6,20,7,1,21,4],[23,3,4,2,7,12,16,7,8,1],[7,1,2,33,4,12,4,18,9,8]]},{"issue":"201810200641","lottery":["4","0","4","4","1"],"pair":[563,554],"leopard":[615,613,616],"group_three":[0,0,0],"group_six":[164,160,173],"total_val":[8,8,9,4,5],"bs_form":["000","000","000"],"oe_form":["000","000","001"],"pc_form":["000","000","000"],"other_form":["101","011","111"],"span":[4,4,3,4,3],"mantissa":[8,8,9,4,5],"miss_data":[[2,6,60,10,4,1,5,3,20,8],["0",4,7,1,2,16,5,3,8,9],[6,3,4,1,4,21,8,2,22,5],[24,4,5,3,4,13,17,1,9,2],[8,1,3,34,1,13,5,19,10,9]]},{"issue":"201810200640","lottery":["5","5","3","0","4"],"pair":[0,555],"leopard":[616,614,617],"group_three":[0,468,452],"group_six":[165,0,0],"total_val":[13,8,7,10,4],"bs_form":["110","100","000"],"oe_form":["111","110","100"],"pc_form":["111","110","100"],"other_form":["220","200","001"],"span":[2,5,4,0,4],"mantissa":[3,8,7,0,4],"miss_data":[[3,7,61,11,1,5,6,4,21,9],[1,5,8,2,3,5,6,4,9,10],[7,4,5,3,1,22,9,3,23,6],["0",5,6,4,1,14,18,2,10,3],[9,1,4,35,4,14,6,20,11,10]]},{"issue":"201810200639","lottery":["2","5","7","1","5"],"pair":[564,556],"leopard":[617,615,618],"group_three":[462,469,453],"group_six":[0,0,0],"total_val":[14,13,13,7,6],"bs_form":["011","110","101"],"oe_form":["011","111","111"],"pc_form":["111","110","101"],"other_form":["221","211","112"],"span":[5,6,6,3,4],"mantissa":[4,3,3,7,6],"miss_data":[[4,8,2,12,2,1,7,5,22,10],[2,6,9,3,4,5,7,5,10,11],[8,5,6,1,2,23,10,7,24,7],[1,1,7,5,2,15,19,3,11,4],[10,2,5,36,1,5,7,21,12,11]]},{"issue":"201810200638","lottery":["4","1","8","1","3"],"pair":[565,557],"leopard":[618,616,619],"group_three":[463,0,454],"group_six":[0,161,0],"total_val":[13,10,12,5,4],"bs_form":["001","010","100"],"oe_form":["010","101","011"],"pc_form":["000","000","001"],"other_form":["112","121","210"],"span":[7,7,7,3,2],"mantissa":[3,0,2,5,4],"miss_data":[[5,9,1,13,4,2,8,6,23,11],[3,1,10,4,5,1,8,6,11,12],[9,6,7,2,3,24,11,1,8,8],[2,1,8,6,3,16,20,4,12,5],[11,3,6,3,2,1,8,22,13,12]]},{"issue":"201810200637","lottery":["6","5","3","3","2"],"pair":[566,558],"leopard":[619,617,620],"group_three":[464,0,0],"group_six":[0,162,174],"total_val":[14,11,8,11,5],"bs_form":["110","100","000"],"oe_form":["011","111","110"],"pc_form":["011","111","111"],"other_form":["020","200","002"],"span":[3,2,1,1,1],"mantissa":[4,1,8,1,5],"miss_data":[[6,10,2,14,1,3,6,7,24,12],[4,1,11,5,6,5,9,7,12,13],[10,7,8,3,4,25,12,2,1,9],[3,1,9,3,4,17,21,5,13,6],[12,4,2,1,3,2,9,23,14,13]]},{"issue":"201810200636","lottery":["6","4","7","0","1"],"pair":[567,559],"leopard":[620,618,621],"group_three":[465,470,455],"group_six":[0,0,0],"total_val":[17,11,8,10,1],"bs_form":["101","010","100"],"oe_form":["001","010","101"],"pc_form":["001","010","100"],"other_form":["011","110","101"],"span":[3,7,7,2,1],"mantissa":[7,1,8,0,1],"miss_data":[[7,11,3,15,2,4,6,8,25,13],[5,2,12,6,4,1,10,8,13,14],[11,8,9,1,5,26,13,7,2,10],["0",2,10,1,5,18,22,6,14,7],[13,1,1,2,4,3,10,24,15,14]]},{"issue":"201810200635","lottery":["5","8","7","4","9"],"pair":[568,560],"leopard":[621,619,622],"group_three":[466,471,456],"group_six":[0,0,0],"total_val":[20,19,20,13,13],"bs_form":["111","110","101"],"oe_form":["101","010","101"],"pc_form":["101","010","100"],"other_form":["221","211","110"],"span":[3,4,5,3,5],"mantissa":[0,9,0,3,3],"miss_data":[[8,12,4,16,3,5,1,9,26,14],[6,3,13,7,1,2,11,9,8,15],[12,9,10,2,6,27,14,7,3,11],[1,3,11,2,4,19,23,7,15,8],[14,1,2,3,5,4,11,25,16,9]]},{"issue":"201810200634","lottery":["6","0","1","2","2"],"pair":[569,0],"leopard":[622,620,623],"group_three":[467,472,0],"group_six":[0,0,175],"total_val":[7,3,5,6,4],"bs_form":["100","000","000"],"oe_form":["001","010","100"],"pc_form":["000","001","011"],"other_form":["001","012","122"],"span":[6,2,1,6,0],"mantissa":[7,3,5,6,4],"miss_data":[[9,13,5,17,4,1,6,10,27,15],["0",4,14,8,2,3,12,10,1,16],[13,1,11,3,7,28,15,1,4,12],[2,4,2,3,1,20,24,8,16,9],[15,2,2,4,6,5,12,26,17,1]]},{"issue":"201810200633","lottery":["3","1","6","3","1"],"pair":[570,561],"leopard":[623,621,624],"group_three":[468,473,457],"group_six":[0,0,0],"total_val":[10,10,10,4,4],"bs_form":["001","010","100"],"oe_form":["110","101","011"],"pc_form":["100","001","010"],"other_form":["010","100","001"],"span":[5,5,5,2,2],"mantissa":[0,0,0,4,4],"miss_data":[[10,14,6,3,5,2,1,11,28,16],[1,1,15,9,3,4,13,11,2,17],[14,1,12,4,8,29,6,2,5,13],[3,5,1,3,2,21,25,9,17,10],[16,1,1,5,7,6,13,27,18,2]]},{"issue":"201810200632","lottery":["6","7","8","5","4"],"pair":[571,562],"leopard":[624,622,625],"group_three":[469,474,458],"group_six":[0,0,0],"total_val":[21,20,17,13,9],"bs_form":["111","111","110"],"oe_form":["010","101","010"],"pc_form":["010","101","010"],"other_form":["012","122","221"],"span":[2,3,4,1,1],"mantissa":[1,0,7,3,9],"miss_data":[[11,15,7,1,6,3,6,12,29,17],[2,1,16,10,4,5,14,7,3,18],[15,2,13,5,9,30,1,3,8,14],[4,6,2,1,3,5,26,10,18,11],[17,1,2,6,4,7,14,28,19,3]]},{"issue":"201810200631","lottery":["5","8","1","1","0"],"pair":[572,563],"leopard":[625,623,626],"group_three":[470,0,0],"group_six":[0,163,176],"total_val":[14,10,2,13,1],"bs_form":["110","100","000"],"oe_form":["101","011","110"],"pc_form":["100","000","000"],"other_form":["221","211","110"],"span":[7,7,1,3,1],"mantissa":[4,0,2,3,1],"miss_data":[[12,16,8,2,7,5,1,13,30,18],[3,2,17,11,5,6,15,1,8,19],[16,1,14,6,10,31,2,4,1,15],[5,1,3,2,4,1,27,11,19,12],["0",2,3,7,1,8,15,29,20,4]]},{"issue":"201810200630","lottery":["3","5","0","9","4"],"pair":[573,564],"leopard":[626,624,627],"group_three":[471,475,459],"group_six":[0,0,0],"total_val":[8,14,13,8,13],"bs_form":["010","101","010"],"oe_form":["110","101","010"],"pc_form":["110","100","000"],"other_form":["020","200","001"],"span":[5,9,9,2,5],"mantissa":[8,4,3,8,3],"miss_data":[[13,17,9,3,8,1,2,14,31,19],[4,3,18,12,6,5,16,2,1,20],["0",1,15,7,11,32,3,5,2,16],[6,1,4,3,5,2,28,12,20,9],[1,3,4,8,4,9,16,30,21,5]]},{"issue":"201810200629","lottery":["2","9","4","4","0"],"pair":[574,565],"leopard":[627,625,628],"group_three":[472,0,0],"group_six":[0,164,177],"total_val":[15,17,8,11,4],"bs_form":["010","100","000"],"oe_form":["010","100","000"],"pc_form":["100","000","000"],"other_form":["201","011","110"],"span":[7,5,4,7,4],"mantissa":[5,7,8,1,4],"miss_data":[[14,18,2,1,9,2,3,15,32,20],[5,4,19,13,7,1,17,3,2,9],[1,2,16,8,4,33,4,6,3,17],[7,2,5,4,4,3,29,13,21,1],["0",4,5,9,1,10,17,31,22,6]]},{"issue":"201810200628","lottery":["2","6","7","7","2"],"pair":[575,566],"leopard":[628,626,629],"group_three":[473,0,0],"group_six":[0,165,178],"total_val":[15,20,16,8,9],"bs_form":["011","111","110"],"oe_form":["001","011","110"],"pc_form":["101","011","111"],"other_form":["201","011","112"],"span":[5,1,5,4,5],"mantissa":[5,0,6,8,9],"miss_data":[[15,19,2,2,10,3,4,16,33,21],[6,5,20,14,8,2,6,4,3,1],[2,3,17,9,1,34,5,7,4,18],[8,3,6,5,1,4,30,7,22,2],[1,5,2,10,2,11,18,32,23,7]]},{"issue":"201810200627","lottery":["8","8","5","6","8"],"pair":[0,567],"leopard":[629,627,630],"group_three":[0,476,460],"group_six":[166,0,0],"total_val":[21,19,19,16,14],"bs_form":["111","111","111"],"oe_form":["001","010","100"],"pc_form":["001","010","100"],"other_form":["222","220","202"],"span":[3,3,3,0,2],"mantissa":[1,9,9,6,4],"miss_data":[[16,20,1,3,11,4,5,17,8,22],[7,6,21,15,9,3,1,5,8,2],[3,4,18,10,2,5,6,1,5,19],[9,4,7,6,2,5,6,1,23,3],[2,6,1,11,3,12,19,33,8,8]]},{"issue":"201810200626","lottery":["9","5","0","2","8"],"pair":[576,568],"leopard":[630,628,631],"group_three":[474,477,461],"group_six":[0,0,0],"total_val":[14,7,10,14,10],"bs_form":["110","100","001"],"oe_form":["110","100","000"],"pc_form":["010","101","010"],"other_form":["020","202","022"],"span":[9,5,8,4,6],"mantissa":[4,7,0,4,0],"miss_data":[[17,21,2,4,12,5,6,18,1,9],[8,7,22,16,10,5,2,6,1,3],["0",5,19,11,3,1,7,2,6,20],[10,5,2,7,3,6,1,2,24,4],[3,7,2,12,4,13,20,34,8,9]]},{"issue":"201810200625","lottery":["9","1","2","8","4"],"pair":[577,569],"leopard":[631,629,632],"group_three":[475,478,462],"group_six":[0,0,0],"total_val":[12,11,14,10,12],"bs_form":["100","001","010"],"oe_form":["110","100","000"],"pc_form":["001","010","100"],"other_form":["012","122","221"],"span":[8,7,6,8,4],"mantissa":[2,1,4,0,2],"miss_data":[[18,22,3,5,13,6,7,19,2,9],[9,1,23,17,11,1,3,7,2,4],[1,6,2,12,4,2,8,3,7,21],[11,6,1,8,4,7,2,3,8,5],[4,8,3,13,4,14,21,35,1,10]]},{"issue":"201810200624","lottery":["4","7","2","4","2"],"pair":[578,570],"leopard":[632,630,633],"group_three":[476,479,0],"group_six":[0,0,179],"total_val":[13,13,8,11,6],"bs_form":["010","100","000"],"oe_form":["010","100","000"],"pc_form":["011","110","101"],"other_form":["112","121","212"],"span":[5,5,2,3,2],"mantissa":[3,3,8,1,6],"miss_data":[[19,23,4,6,4,7,8,20,3,1],[10,1,24,18,12,2,4,7,3,5],[2,7,2,13,5,3,9,4,8,22],[12,7,2,9,4,8,3,4,1,6],[5,9,2,14,1,15,22,36,2,11]]},{"issue":"201810200623","lottery":["6","4","2","4","2"],"pair":[579,571],"leopard":[633,631,634],"group_three":[477,0,0],"group_six":[0,166,180],"total_val":[12,10,8,10,6],"bs_form":["100","000","000"],"oe_form":["000","000","000"],"pc_form":["001","010","101"],"other_form":["012","121","212"],"span":[4,2,2,2,2],"mantissa":[2,0,8,0,6],"miss_data":[[20,24,5,7,1,8,6,21,4,2],[11,2,25,19,4,3,5,1,4,6],[3,8,2,14,6,4,10,5,9,23],[13,8,3,10,4,9,4,5,2,7],[6,10,2,15,2,16,23,37,3,12]]},{"issue":"201810200622","lottery":["7","1","2","1","9"],"pair":[580,572],"leopard":[634,632,635],"group_three":[478,0,463],"group_six":[0,167,0],"total_val":[10,4,12,8,10],"bs_form":["100","000","001"],"oe_form":["110","101","011"],"pc_form":["101","010","100"],"other_form":["112","121","210"],"span":[6,1,8,6,8],"mantissa":[0,4,2,8,0],"miss_data":[[21,25,6,8,2,9,1,7,5,3],[12,1,26,20,1,4,6,2,5,7],[4,9,2,15,7,5,11,6,10,24],[14,1,4,11,1,10,5,6,3,8],[7,11,1,16,3,17,24,38,4,9]]},{"issue":"201810200621","lottery":["3","7","0","6","8"],"pair":[581,573],"leopard":[635,633,636],"group_three":[479,480,464],"group_six":[0,0,0],"total_val":[10,13,14,10,14],"bs_form":["010","101","011"],"oe_form":["110","100","000"],"pc_form":["110","100","000"],"other_form":["010","100","002"],"span":[7,7,8,4,2],"mantissa":[0,3,4,0,4],"miss_data":[[22,26,7,3,3,10,2,1,6,4],[13,1,27,21,2,5,7,7,6,8],["0",10,1,16,8,6,12,7,11,25],[15,1,5,12,2,11,6,7,4,9],[8,12,2,17,4,18,25,39,8,1]]},{"issue":"201810200620","lottery":["4","6","9","0","8"],"pair":[582,574],"leopard":[636,634,637],"group_three":[480,481,465],"group_six":[0,0,0],"total_val":[19,15,17,10,8],"bs_form":["011","110","101"],"oe_form":["001","010","100"],"pc_form":["000","000","000"],"other_form":["100","000","002"],"span":[5,9,9,2,8],"mantissa":[9,5,7,0,8],"miss_data":[[23,27,8,1,4,11,3,2,7,5],[14,2,28,22,3,6,6,1,7,9],[1,11,2,17,9,7,13,8,12,9],["0",2,6,13,3,12,1,8,5,10],[9,13,3,18,5,19,26,40,8,2]]},{"issue":"201810200619","lottery":["2","3","7","5","4"],"pair":[583,575],"leopard":[637,635,638],"group_three":[481,482,466],"group_six":[0,0,0],"total_val":[12,15,16,5,9],"bs_form":["001","011","110"],"oe_form":["011","111","110"],"pc_form":["111","111","110"],"other_form":["201","012","121"],"span":[5,4,3,1,1],"mantissa":[2,5,6,5,9],"miss_data":[[24,28,2,2,1,12,4,3,8,6],[15,3,29,3,4,7,1,2,8,10],[2,12,3,18,10,8,14,7,13,1],[1,3,7,14,4,5,2,9,6,11],[10,14,4,19,4,20,27,41,1,3]]},{"issue":"201810200618","lottery":["6","1","3","7","3"],"pair":[584,576],"leopard":[638,636,639],"group_three":[482,483,0],"group_six":[0,0,181],"total_val":[10,11,13,7,10],"bs_form":["100","001","010"],"oe_form":["011","111","111"],"pc_form":["001","011","111"],"other_form":["010","101","010"],"span":[5,6,4,5,4],"mantissa":[0,1,3,7,0],"miss_data":[[25,29,1,3,2,13,6,4,9,7],[16,1,30,1,5,8,2,3,9,11],[3,13,4,3,11,9,15,1,14,2],[2,4,8,15,5,1,3,7,7,12],[11,15,5,3,1,21,28,42,2,4]]},{"issue":"201810200617","lottery":["2","7","0","7","8"],"pair":[585,577],"leopard":[639,637,640],"group_three":[483,0,467],"group_six":[0,168,0],"total_val":[9,14,15,9,15],"bs_form":["010","101","011"],"oe_form":["010","101","010"],"pc_form":["110","101","010"],"other_form":["210","101","012"],"span":[7,7,8,5,1],"mantissa":[9,4,5,9,5],"miss_data":[[26,30,2,4,3,14,1,5,10,8],[17,1,31,2,6,9,3,7,10,12],["0",14,5,1,12,10,16,2,15,3],[3,5,9,16,6,2,4,7,8,13],[12,16,6,1,2,22,29,43,8,5]]},{"issue":"201810200616","lottery":["4","7","9","7","1"],"pair":[586,578],"leopard":[640,638,641],"group_three":[484,0,468],"group_six":[0,169,0],"total_val":[20,23,17,11,8],"bs_form":["011","111","110"],"oe_form":["011","111","111"],"pc_form":["010","101","010"],"other_form":["110","101","011"],"span":[5,2,8,3,6],"mantissa":[0,3,7,1,8],"miss_data":[[27,31,1,5,4,15,2,6,11,9],[18,2,32,3,7,10,4,7,11,13],[1,15,6,2,13,11,17,3,16,9],[4,6,10,17,7,3,5,7,9,14],[13,1,7,2,3,23,30,44,1,6]]},{"issue":"201810200615","lottery":["3","5","2","9","7"],"pair":[587,579],"leopard":[641,639,642],"group_three":[485,484,469],"group_six":[0,0,0],"total_val":[10,16,18,8,16],"bs_form":["010","101","011"],"oe_form":["110","101","011"],"pc_form":["111","110","101"],"other_form":["022","220","201"],"span":[3,7,7,2,2],"mantissa":[0,6,8,8,6],"miss_data":[[28,32,2,3,1,16,3,7,12,10],[19,3,33,4,8,5,5,1,12,14],[2,16,2,3,14,12,18,4,17,1],[5,7,11,18,8,4,6,1,10,9],[14,1,8,3,4,24,31,7,2,7]]},{"issue":"201810200614","lottery":["8","3","7","5","3"],"pair":[588,580],"leopard":[642,640,643],"group_three":[486,485,470],"group_six":[0,0,0],"total_val":[18,15,15,11,8],"bs_form":["101","011","110"],"oe_form":["011","111","111"],"pc_form":["011","111","111"],"other_form":["201","012","120"],"span":[5,4,4,5,2],"mantissa":[8,5,5,1,8],"miss_data":[[29,33,3,1,2,17,4,8,8,11],[20,4,34,3,9,1,6,2,13,15],[3,17,1,4,15,13,19,7,18,2],[6,8,12,19,9,5,7,2,11,1],[15,2,9,3,5,25,32,1,3,8]]},{"issue":"201810200613","lottery":["3","5","2","4","5"],"pair":[589,581],"leopard":[643,641,644],"group_three":[487,486,471],"group_six":[0,0,0],"total_val":[10,11,11,8,9],"bs_form":["010","100","001"],"oe_form":["110","100","001"],"pc_form":["111","110","101"],"other_form":["022","221","212"],"span":[3,3,3,2,1],"mantissa":[0,1,1,8,9],"miss_data":[[30,34,4,3,3,18,5,9,1,12],[21,5,35,1,10,5,7,3,14,16],[4,18,2,5,16,14,20,1,19,3],[7,9,13,20,4,1,8,3,12,2],[16,3,10,1,6,5,33,2,4,9]]},{"issue":"201810200612","lottery":["1","6","1","3","4"],"pair":[590,582],"leopard":[644,642,645],"group_three":[0,487,472],"group_six":[167,0,0],"total_val":[8,10,8,7,7],"bs_form":["010","100","000"],"oe_form":["101","011","110"],"pc_form":["000","001","010"],"other_form":["101","010","101"],"span":[5,5,3,5,1],"mantissa":[8,0,8,7,7],"miss_data":[[31,1,5,1,4,19,6,10,2,13],[22,6,36,2,11,1,6,4,15,17],[5,1,1,6,17,15,21,2,20,4],[8,10,14,3,1,2,9,4,13,3],[17,4,11,2,4,1,34,3,5,10]]},{"issue":"201810200611","lottery":["1","1","2","0","6"],"pair":[0,583],"leopard":[645,643,646],"group_three":[0,488,473],"group_six":[168,0,0],"total_val":[4,3,8,2,6],"bs_form":["000","000","001"],"oe_form":["110","100","000"],"pc_form":["001","010","100"],"other_form":["112","120","200"],"span":[1,2,6,0,6],"mantissa":[4,3,8,2,6],"miss_data":[[32,1,6,2,5,20,7,11,3,14],[23,1,37,3,12,2,1,5,16,18],[6,1,2,7,18,16,22,3,21,5],["0",11,15,1,2,3,10,5,14,4],[18,5,12,3,1,2,6,4,6,11]]},{"issue":"201810200610","lottery":["9","9","8","1","7"],"pair":[0,584],"leopard":[646,644,647],"group_three":[0,489,474],"group_six":[169,0,0],"total_val":[26,18,16,18,8],"bs_form":["111","110","101"],"oe_form":["110","101","011"],"pc_form":["000","000","001"],"other_form":["002","021","211"],"span":[1,8,7,0,6],"mantissa":[6,8,6,8,8],"miss_data":[[33,1,7,3,6,21,8,12,4,9],[24,1,38,4,13,3,2,6,17,9],[7,2,1,8,19,17,23,4,8,6],[1,1,16,2,3,4,11,6,15,5],[19,6,13,4,2,3,1,7,7,12]]},{"issue":"201810200609","lottery":["9","0","5","5","3"],"pair":[591,585],"leopard":[647,645,648],"group_three":[488,0,0],"group_six":[0,170,182],"total_val":[14,10,13,9,8],"bs_form":["101","011","110"],"oe_form":["101","011","111"],"pc_form":["001","011","111"],"other_form":["002","022","220"],"span":[9,5,2,9,2],"mantissa":[4,0,3,9,8],"miss_data":[[34,2,8,4,7,22,9,13,5,9],["0",2,39,5,14,4,3,7,18,1],[8,3,2,9,20,5,24,5,1,7],[2,1,17,3,4,5,12,7,16,6],[20,7,14,3,3,4,2,1,8,13]]},{"issue":"201810200608","lottery":["1","0","3","2","3"],"pair":[592,586],"leopard":[648,646,649],"group_three":[489,490,0],"group_six":[0,0,183],"total_val":[4,5,8,1,5],"bs_form":["000","000","000"],"oe_form":["101","010","101"],"pc_form":["001","011","111"],"other_form":["100","002","020"],"span":[3,3,1,1,1],"mantissa":[4,5,8,1,5],"miss_data":[[35,1,9,5,8,23,10,14,6,1],["0",3,40,6,15,5,4,8,19,2],[9,4,3,3,21,1,25,6,2,8],[3,2,2,4,5,1,13,8,17,7],[21,8,15,3,4,5,3,2,9,14]]},{"issue":"201810200607","lottery":["3","6","9","5","1"],"pair":[593,587],"leopard":[649,647,650],"group_three":[490,491,475],"group_six":[0,0,0],"total_val":[18,20,15,9,6],"bs_form":["011","111","110"],"oe_form":["101","011","111"],"pc_form":["100","001","010"],"other_form":["000","002","021"],"span":[6,4,8,3,4],"mantissa":[8,0,5,9,6],"miss_data":[[36,1,10,3,9,24,11,15,7,2],[1,4,41,7,16,6,6,9,20,3],[10,5,4,1,22,2,26,7,3,9],[4,3,1,5,6,5,14,9,18,8],[22,1,16,1,5,6,4,3,10,15]]},{"issue":"201810200606","lottery":["1","5","4","1","2"],"pair":[594,588],"leopard":[650,648,651],"group_three":[491,492,476],"group_six":[0,0,0],"total_val":[10,10,7,6,3],"bs_form":["010","100","000"],"oe_form":["110","101","010"],"pc_form":["010","100","001"],"other_form":["121","211","112"],"span":[4,4,3,4,1],"mantissa":[0,0,7,6,3],"miss_data":[[37,1,11,1,10,25,12,16,8,3],[2,5,42,8,17,5,1,10,21,4],[11,6,5,2,4,3,27,8,4,1],[5,1,2,6,7,1,15,10,19,9],[23,1,2,2,6,7,5,4,11,16]]},{"issue":"201810200605","lottery":["9","6","6","5","4"],"pair":[595,589],"leopard":[651,649,652],"group_three":[0,0,477],"group_six":[170,171,0],"total_val":[21,17,15,15,9],"bs_form":["111","111","110"],"oe_form":["100","001","010"],"pc_form":["000","001","010"],"other_form":["000","002","021"],"span":[3,1,2,3,1],"mantissa":[1,7,5,5,9],"miss_data":[[38,1,12,2,11,26,13,17,9,9],[3,6,43,9,18,1,6,11,22,5],[12,7,6,3,1,4,6,9,5,2],[6,1,3,7,8,5,16,11,20,10],[24,2,1,3,4,8,6,5,12,17]]},{"issue":"201810200604","lottery":["3","1","0","8","3"],"pair":[596,590],"leopard":[652,650,653],"group_three":[492,493,478],"group_six":[0,0,0],"total_val":[4,9,11,4,11],"bs_form":["000","001","010"],"oe_form":["110","100","001"],"pc_form":["100","000","001"],"other_form":["010","102","020"],"span":[3,8,8,2,5],"mantissa":[4,9,1,4,1],"miss_data":[[39,2,13,3,12,27,14,18,10,1],[4,1,44,10,19,2,1,12,23,6],["0",8,7,4,2,5,1,10,6,3],[7,2,4,8,9,1,17,12,8,11],[25,3,2,3,1,9,7,6,13,18]]},{"issue":"201810200603","lottery":["0","6","7","4","3"],"pair":[597,591],"leopard":[653,651,654],"group_three":[493,494,479],"group_six":[0,0,0],"total_val":[13,17,14,6,7],"bs_form":["011","110","100"],"oe_form":["001","010","101"],"pc_form":["001","010","101"],"other_form":["001","011","110"],"span":[7,3,4,6,1],"mantissa":[3,7,4,6,7],"miss_data":[["0",3,14,1,13,28,15,19,11,2],[5,1,45,11,20,3,6,13,24,7],[1,9,8,5,3,6,2,7,7,4],[8,3,5,9,4,2,18,13,1,12],[26,4,3,3,2,10,8,7,14,19]]},{"issue":"201810200602","lottery":["7","0","7","2","2"],"pair":[598,0],"leopard":[654,652,655],"group_three":[0,495,0],"group_six":[171,0,184],"total_val":[14,9,11,7,4],"bs_form":["101","010","100"],"oe_form":["101","010","100"],"pc_form":["101","011","111"],"other_form":["101","012","122"],"span":[7,7,5,7,0],"mantissa":[4,9,1,7,4],"miss_data":[[1,4,15,2,14,29,16,7,12,3],["0",2,46,12,21,4,1,14,25,8],[2,10,9,6,4,7,3,7,8,5],[9,4,2,10,1,3,19,14,2,13],[27,5,2,1,3,11,9,8,15,20]]},{"issue":"201810200601","lottery":["9","9","0","4","6"],"pair":[0,592],"leopard":[655,653,656],"group_three":[0,496,480],"group_six":[172,0,0],"total_val":[18,13,10,18,10],"bs_form":["110","100","001"],"oe_form":["110","100","000"],"pc_form":["000","000","000"],"other_form":["000","001","010"],"span":[9,9,6,0,2],"mantissa":[8,3,0,8,0],"miss_data":[[2,5,16,3,15,30,17,1,13,9],[1,3,47,13,22,5,2,15,26,9],["0",11,10,7,5,8,4,1,9,6],[10,5,1,11,4,4,20,15,3,14],[28,6,1,2,4,12,6,9,16,21]]},{"issue":"201810200600","lottery":["1","4","4","1","1"],"pair":[599,0],"leopard":[656,654,657],"group_three":[0,0,0],"group_six":[173,172,185],"total_val":[9,9,6,5,2],"bs_form":["000","000","000"],"oe_form":["100","001","011"],"pc_form":["000","000","000"],"other_form":["111","111","111"],"span":[3,3,3,3,0],"mantissa":[9,9,6,5,2],"miss_data":[[3,1,17,4,16,31,18,2,14,1],[2,4,48,14,4,6,3,16,27,1],[1,12,11,8,4,9,5,2,10,7],[11,1,2,12,1,5,21,16,4,15],[29,1,2,3,5,13,1,10,17,22]]}],"statistics_data":[]}}